[{"w":"Why"},{"w":"People"},{"w":"Closest"},{"w":"to"},{"w":"Reality"},{"w":"Suffer","p":"separator"},{"w":"It"},{"w":"does"},{"w":"not"},{"w":"happen"},{"w":"in"},{"w":"a"},{"w":"crisis"},{"w":"or"},{"w":"a"},{"w":"confrontation.","p":"sentence"},{"w":"It"},{"w":"is"},{"w":"quieter"},{"w":"than"},{"w":"that.","p":"paragraph"},{"w":"A"},{"w":"principal"},{"w":"engineer"},{"w":"at"},{"w":"an"},{"w":"online"},{"w":"fashion"},{"w":"marketplace"},{"w":"raises"},{"w":"a"},{"w":"concern"},{"w":"about"},{"w":"a"},{"w":"dependency"},{"w":"that"},{"w":"will"},{"w":"block"},{"w":"the"},{"w":"roadmap.","p":"sentence"},{"w":"The"},{"w":"concern"},{"w":"is"},{"w":"noted"},{"w":"but"},{"w":"not"},{"w":"addressed.","p":"sentence"},{"w":"She"},{"w":"flags"},{"w":"a"},{"w":"risk"},{"w":"in"},{"w":"an"},{"w":"architecture"},{"w":"review.","p":"sentence"},{"w":"The"},{"w":"risk"},{"w":"is"},{"w":"acknowledged"},{"w":"but"},{"w":"deprioritised.","p":"sentence"},{"w":"She"},{"w":"points"},{"w":"out"},{"w":"that"},{"w":"a"},{"w":"commitment"},{"w":"made"},{"w":"to"},{"w":"the"},{"w":"board"},{"w":"cannot"},{"w":"be"},{"w":"delivered"},{"w":"as"},{"w":"described.","p":"sentence"},{"w":"She"},{"w":"is"},{"w":"told"},{"w":"to"},{"w":"“find"},{"w":"a"},{"w":"way.”"},{"w":"She"},{"w":"suggests"},{"w":"an"},{"w":"alternative"},{"w":"approach"},{"w":"that"},{"w":"would"},{"w":"achieve"},{"w":"the"},{"w":"goal"},{"w":"more"},{"w":"reliably.","p":"sentence"},{"w":"The"},{"w":"suggestion"},{"w":"is"},{"w":"described"},{"w":"as"},{"w":"“too"},{"w":"technical”"},{"w":"for"},{"w":"the"},{"w":"current"},{"w":"discussion.","p":"paragraph"},{"w":"After"},{"w":"enough"},{"w":"of"},{"w":"these"},{"w":"exchanges,","p":"comma"},{"w":"she"},{"w":"stops.","p":"sentence"},{"w":"Not"},{"w":"because"},{"w":"she"},{"w":"has"},{"w":"lost"},{"w":"the"},{"w":"knowledge.","p":"sentence"},{"w":"She"},{"w":"still"},{"w":"sees"},{"w":"the"},{"w":"problems"},{"w":"clearly,","p":"comma"},{"w":"still"},{"w":"traces"},{"w":"the"},{"w":"dependencies"},{"w":"in"},{"w":"her"},{"w":"head,","p":"comma"},{"w":"still"},{"w":"knows"},{"w":"which"},{"w":"parts"},{"w":"of"},{"w":"the"},{"w":"system"},{"w":"are"},{"w":"fragile"},{"w":"and"},{"w":"why.","p":"sentence"},{"w":"But"},{"w":"the"},{"w":"cost"},{"w":"of"},{"w":"stating"},{"w":"what"},{"w":"she"},{"w":"sees"},{"w":"has"},{"w":"become"},{"w":"higher"},{"w":"than"},{"w":"the"},{"w":"cost"},{"w":"of"},{"w":"staying"},{"w":"silent.","p":"sentence"},{"w":"She"},{"w":"learns"},{"w":"that"},{"w":"the"},{"w":"organisation"},{"w":"does"},{"w":"not"},{"w":"want"},{"w":"the"},{"w":"information"},{"w":"she"},{"w":"has.","p":"sentence"},{"w":"It"},{"w":"wants"},{"w":"compliance"},{"w":"wrapped"},{"w":"in"},{"w":"technical"},{"w":"language.","p":"paragraph"},{"w":"An"},{"w":"operations"},{"w":"analyst"},{"w":"at"},{"w":"a"},{"w":"logistics"},{"w":"company"},{"w":"maintains"},{"w":"a"},{"w":"spreadsheet"},{"w":"that"},{"w":"nobody"},{"w":"asked"},{"w":"her"},{"w":"to"},{"w":"create.","p":"paragraph"},{"w":"It"},{"w":"tracks"},{"w":"every"},{"w":"exception"},{"w":"in"},{"w":"the"},{"w":"fulfilment"},{"w":"process:","p":"comma"},{"w":"the"},{"w":"customers"},{"w":"whose"},{"w":"orders"},{"w":"require"},{"w":"manual"},{"w":"intervention,","p":"comma"},{"w":"the"},{"w":"carrier"},{"w":"routes"},{"w":"where"},{"w":"the"},{"w":"standard"},{"w":"SLA"},{"w":"does"},{"w":"not"},{"w":"apply,","p":"comma"},{"w":"the"},{"w":"product"},{"w":"categories"},{"w":"that"},{"w":"need"},{"w":"special"},{"w":"handling"},{"w":"documentation,","p":"comma"},{"w":"the"},{"w":"warehouses"},{"w":"where"},{"w":"the"},{"w":"inventory"},{"w":"system's"},{"w":"count"},{"w":"diverges"},{"w":"from"},{"w":"physical"},{"w":"stock"},{"w":"by"},{"w":"more"},{"w":"than"},{"w":"the"},{"w":"acceptable"},{"w":"threshold.","p":"sentence"},{"w":"The"},{"w":"spreadsheet"},{"w":"has"},{"w":"forty-"},{"w":"seven"},{"w":"columns.","p":"sentence"},{"w":"She"},{"w":"updates"},{"w":"it"},{"w":"daily.","p":"sentence"},{"w":"It"},{"w":"is"},{"w":"the"},{"w":"only"},{"w":"accurate"},{"w":"record"},{"w":"of"},{"w":"how"},{"w":"the"},{"w":"fulfilment"},{"w":"process"},{"w":"actually"},{"w":"works,","p":"comma"},{"w":"as"},{"w":"opposed"},{"w":"to"},{"w":"how"},{"w":"the"},{"w":"system"},{"w":"says"},{"w":"it"},{"w":"works.","p":"paragraph"},{"w":"When"},{"w":"the"},{"w":"company"},{"w":"decides"},{"w":"to"},{"w":"replace"},{"w":"its"},{"w":"order"},{"w":"management"},{"w":"system,","p":"comma"},{"w":"nobody"},{"w":"consults"},{"w":"her.","p":"sentence"},{"w":"The"},{"w":"requirements"},{"w":"are"},{"w":"gathered"},{"w":"from"},{"w":"process"},{"w":"owners"},{"w":"who"},{"w":"describe"},{"w":"the"},{"w":"process"},{"w":"as"},{"w":"it"},{"w":"is"},{"w":"documented,","p":"comma"},{"w":"not"},{"w":"as"},{"w":"it"},{"w":"operates.","p":"sentence"},{"w":"The"},{"w":"new"},{"w":"system"},{"w":"is"},{"w":"specified,","p":"comma"},{"w":"built,","p":"comma"},{"w":"and"},{"w":"launched"},{"w":"over"},{"w":"fourteen"},{"w":"months.","p":"paragraph"},{"w":"Within"},{"w":"three"},{"w":"weeks"},{"w":"of"},{"w":"go-"},{"w":"live,","p":"comma"},{"w":"the"},{"w":"same"},{"w":"exceptions"},{"w":"return.","p":"sentence"},{"w":"Carriers"},{"w":"flag"},{"w":"shipments"},{"w":"that"},{"w":"do"},{"w":"not"},{"w":"meet"},{"w":"special"},{"w":"handling"},{"w":"requirements.","p":"sentence"},{"w":"Warehouse"},{"w":"staff"},{"w":"discover"},{"w":"that"},{"w":"the"},{"w":"inventory"},{"w":"reconciliation"},{"w":"logic"},{"w":"does"},{"w":"not"},{"w":"account"},{"w":"for"},{"w":"the"},{"w":"discrepancies"},{"w":"they"},{"w":"have"},{"w":"been"},{"w":"managing"},{"w":"manually"},{"w":"for"},{"w":"years.","p":"sentence"},{"w":"Customer"},{"w":"service"},{"w":"begins"},{"w":"receiving"},{"w":"complaints"},{"w":"about"},{"w":"orders"},{"w":"that"},{"w":"the"},{"w":"old"},{"w":"system"},{"w":"would"},{"w":"have"},{"w":"routed"},{"w":"to"},{"w":"manual"},{"w":"review"},{"w":"but"},{"w":"the"},{"w":"new"},{"w":"system"},{"w":"processes"},{"w":"automatically,","p":"comma"},{"w":"and"},{"w":"incorrectly.","p":"paragraph"},{"w":"She"},{"w":"rebuilds"},{"w":"the"},{"w":"spreadsheet.","p":"sentence"},{"w":"It"},{"w":"takes"},{"w":"her"},{"w":"two"},{"w":"weeks.","p":"sentence"},{"w":"She"},{"w":"adds"},{"w":"twelve"},{"w":"new"},{"w":"columns"},{"w":"for"},{"w":"exception"},{"w":"types"},{"w":"that"},{"w":"the"},{"w":"new"},{"w":"system"},{"w":"has"},{"w":"introduced.","p":"sentence"},{"w":"Nobody"},{"w":"asks"},{"w":"where"},{"w":"the"},{"w":"spreadsheet"},{"w":"came"},{"w":"from,","p":"comma"},{"w":"or"},{"w":"why"},{"w":"it"},{"w":"is"},{"w":"necessary,","p":"comma"},{"w":"or"},{"w":"what"},{"w":"it"},{"w":"implies"},{"w":"about"},{"w":"the"},{"w":"system"},{"w":"that"},{"w":"was"},{"w":"supposed"},{"w":"to"},{"w":"replace"},{"w":"it.","p":"paragraph"},{"w":"Her"},{"w":"manager"},{"w":"praises"},{"w":"the"},{"w":"new"},{"w":"system"},{"w":"in"},{"w":"a"},{"w":"quarterly"},{"w":"review.","p":"sentence"},{"w":"He"},{"w":"mentions"},{"w":"that"},{"w":"the"},{"w":"transition"},{"w":"was"},{"w":"completed"},{"w":"on"},{"w":"time"},{"w":"and"},{"w":"under"},{"w":"budget.","p":"sentence"},{"w":"He"},{"w":"makes"},{"w":"no"},{"w":"mention"},{"w":"of"},{"w":"the"},{"w":"spreadsheet,","p":"comma"},{"w":"as"},{"w":"he"},{"w":"remains"},{"w":"entirely"},{"w":"unaware"},{"w":"of"},{"w":"its"},{"w":"existence.","p":"paragraph"},{"w":"While"},{"w":"the"},{"w":"industry"},{"w":"and"},{"w":"specific"},{"w":"roles"},{"w":"evolve,","p":"comma"},{"w":"the"},{"w":"underlying"},{"w":"pattern"},{"w":"remains"},{"w":"remarkably"},{"w":"consistent.","p":"separator"},{"w":"In"},{"w":"software-"},{"w":"dependent"},{"w":"corporates,","p":"comma"},{"w":"the"},{"w":"people"},{"w":"who"},{"w":"suffer"},{"w":"first"},{"w":"are"},{"w":"not"},{"w":"the"},{"w":"least"},{"w":"capable.","p":"sentence"},{"w":"They"},{"w":"are"},{"w":"the"},{"w":"most"},{"w":"reality-"},{"w":"bound.","p":"paragraph"},{"w":"They"},{"w":"are"},{"w":"the"},{"w":"people"},{"w":"whose"},{"w":"effectiveness"},{"w":"depends"},{"w":"on"},{"w":"clear"},{"w":"ownership,","p":"comma"},{"w":"explicit"},{"w":"constraints,","p":"comma"},{"w":"and"},{"w":"contact"},{"w":"with"},{"w":"how"},{"w":"systems"},{"w":"actually"},{"w":"behave.","p":"sentence"},{"w":"They"},{"w":"notice"},{"w":"incoherence"},{"w":"early.","p":"sentence"},{"w":"They"},{"w":"see"},{"w":"the"},{"w":"cost"},{"w":"of"},{"w":"ambiguity"},{"w":"before"},{"w":"it"},{"w":"shows"},{"w":"up"},{"w":"in"},{"w":"financial"},{"w":"results"},{"w":"or"},{"w":"executive"},{"w":"dashboards.","p":"sentence"},{"w":"They"},{"w":"can"},{"w":"tell"},{"w":"when"},{"w":"a"},{"w":"plan"},{"w":"is"},{"w":"not"},{"w":"merely"},{"w":"optimistic"},{"w":"but"},{"w":"structurally"},{"w":"impossible.","p":"paragraph"},{"w":"Within"},{"w":"a"},{"w":"coherent"},{"w":"organisation,","p":"comma"},{"w":"such"},{"w":"a"},{"w":"focus"},{"w":"serves"},{"w":"as"},{"w":"a"},{"w":"distinct"},{"w":"advantage.","p":"paragraph"},{"w":"However,","p":"comma"},{"w":"within"},{"w":"a"},{"w":"software-"},{"w":"dependent"},{"w":"corporate,","p":"comma"},{"w":"it"},{"w":"quickly"},{"w":"becomes"},{"w":"a"},{"w":"severe"},{"w":"professional"},{"w":"liability.","p":"paragraph"},{"w":"These"},{"w":"organisations"},{"w":"do"},{"w":"not"},{"w":"fail"},{"w":"to"},{"w":"reward"},{"w":"competence"},{"w":"because"},{"w":"they"},{"w":"dislike"},{"w":"competence.","p":"sentence"},{"w":"They"},{"w":"fail"},{"w":"to"},{"w":"reward"},{"w":"it"},{"w":"because"},{"w":"competence"},{"w":"collapses"},{"w":"options.","p":"sentence"},{"w":"It"},{"w":"reduces"},{"w":"the"},{"w":"space"},{"w":"in"},{"w":"which"},{"w":"narratives"},{"w":"can"},{"w":"remain"},{"w":"unchallenged.","p":"sentence"},{"w":"It"},{"w":"forces"},{"w":"decisions"},{"w":"to"},{"w":"become"},{"w":"specific,","p":"comma"},{"w":"which"},{"w":"forces"},{"w":"responsibility"},{"w":"to"},{"w":"become"},{"w":"local.","p":"sentence"},{"w":"And"},{"w":"local"},{"w":"responsibility"},{"w":"is"},{"w":"threatening"},{"w":"to"},{"w":"hierarchies"},{"w":"that"},{"w":"have"},{"w":"learned"},{"w":"to"},{"w":"operate"},{"w":"through"},{"w":"diffusion.","p":"paragraph"},{"w":"Optional"},{"w":"reality"},{"w":"is"},{"w":"comfortable"},{"w":"for"},{"w":"hierarchies.","p":"sentence"},{"w":"It"},{"w":"allows"},{"w":"authority"},{"w":"to"},{"w":"speak"},{"w":"in"},{"w":"intent"},{"w":"rather"},{"w":"than"},{"w":"mechanism.","p":"sentence"},{"w":"It"},{"w":"allows"},{"w":"strategy"},{"w":"to"},{"w":"be"},{"w":"expressed"},{"w":"as"},{"w":"aspiration"},{"w":"rather"},{"w":"than"},{"w":"constraint.","p":"sentence"},{"w":"It"},{"w":"allows"},{"w":"ownership"},{"w":"to"},{"w":"be"},{"w":"proclaimed"},{"w":"without"},{"w":"being"},{"w":"enforced.","p":"paragraph"},{"w":"People"},{"w":"closest"},{"w":"to"},{"w":"reality"},{"w":"disrupt"},{"w":"this"},{"w":"comfort"},{"w":"by"},{"w":"insisting"},{"w":"on"},{"w":"the"},{"w":"medium"},{"w":"that"},{"w":"hierarchies"},{"w":"would"},{"w":"rather"},{"w":"avoid:","p":"comma"},{"w":"the"},{"w":"system"},{"w":"itself.","p":"paragraph"},{"w":"The"},{"w":"resulting"},{"w":"tension"},{"w":"is"},{"w":"often"},{"w":"misdiagnosed"},{"w":"as"},{"w":"a"},{"w":"communication"},{"w":"issue.","p":"sentence"},{"w":"Engineers"},{"w":"are"},{"w":"told"},{"w":"they"},{"w":"need"},{"w":"to"},{"w":"be"},{"w":"more"},{"w":"commercial,","p":"comma"},{"w":"more"},{"w":"customer-"},{"w":"centric,","p":"comma"},{"w":"or"},{"w":"more"},{"w":"aligned.","p":"sentence"},{"w":"Product"},{"w":"managers"},{"w":"are"},{"w":"told"},{"w":"they"},{"w":"need"},{"w":"to"},{"w":"translate"},{"w":"better.","p":"sentence"},{"w":"“Tech"},{"w":"and"},{"w":"business"},{"w":"alignment”"},{"w":"becomes"},{"w":"a"},{"w":"recurring"},{"w":"item"},{"w":"on"},{"w":"the"},{"w":"leadership"},{"w":"agenda,","p":"comma"},{"w":"addressed"},{"w":"through"},{"w":"workshops,","p":"comma"},{"w":"pairing"},{"w":"programmes,","p":"comma"},{"w":"and"},{"w":"communication"},{"w":"skills"},{"w":"training"},{"w":"that"},{"w":"never"},{"w":"touch"},{"w":"the"},{"w":"underlying"},{"w":"problem,","p":"comma"},{"w":"because"},{"w":"the"},{"w":"underlying"},{"w":"problem"},{"w":"is"},{"w":"not"},{"w":"that"},{"w":"people"},{"w":"are"},{"w":"failing"},{"w":"to"},{"w":"communicate.","p":"sentence"},{"w":"It"},{"w":"is"},{"w":"that"},{"w":"reality"},{"w":"is"},{"w":"being"},{"w":"negotiated"},{"w":"instead"},{"w":"of"},{"w":"maintained.","p":"paragraph"},{"w":"In"},{"w":"such"},{"w":"an"},{"w":"environment,","p":"comma"},{"w":"they"},{"w":"face"},{"w":"a"},{"w":"consistent"},{"w":"set"},{"w":"of"},{"w":"punishments.","p":"sentence"},{"w":"These"},{"w":"punishments"},{"w":"are"},{"w":"rarely"},{"w":"made"},{"w":"explicit;","p":"comma"},{"w":"instead,","p":"comma"},{"w":"they"},{"w":"are"},{"w":"embedded"},{"w":"within"},{"w":"the"},{"w":"organisation's"},{"w":"structure.","p":"paragraph"},{"w":"They"},{"w":"are"},{"w":"asked"},{"w":"to"},{"w":"estimate"},{"w":"work"},{"w":"whose"},{"w":"scope"},{"w":"is"},{"w":"undefined,","p":"comma"},{"w":"against"},{"w":"deadlines"},{"w":"whose"},{"w":"origins"},{"w":"are"},{"w":"political"},{"w":"rather"},{"w":"than"},{"w":"technical.","p":"sentence"},{"w":"They"},{"w":"are"},{"w":"asked"},{"w":"to"},{"w":"build"},{"w":"systems"},{"w":"around"},{"w":"boundaries"},{"w":"that"},{"w":"do"},{"w":"not"},{"w":"exist,","p":"comma"},{"w":"to"},{"w":"treat"},{"w":"slideware"},{"w":"as"},{"w":"constraints,","p":"comma"},{"w":"and"},{"w":"to"},{"w":"accept"},{"w":"accountability"},{"w":"for"},{"w":"outcomes"},{"w":"they"},{"w":"cannot"},{"w":"influence.","p":"sentence"},{"w":"They"},{"w":"are"},{"w":"expected"},{"w":"to"},{"w":"say"},{"w":"“yes”"},{"w":"to"},{"w":"plans"},{"w":"they"},{"w":"know"},{"w":"will"},{"w":"fail,","p":"comma"},{"w":"because"},{"w":"saying"},{"w":"“no”"},{"w":"creates"},{"w":"friction"},{"w":"and"},{"w":"honest"},{"w":"estimates"},{"w":"imply"},{"w":"timelines"},{"w":"that"},{"w":"stakeholders"},{"w":"do"},{"w":"not"},{"w":"want"},{"w":"to"},{"w":"hear.","p":"paragraph"},{"w":"If"},{"w":"they"},{"w":"refuse"},{"w":"to"},{"w":"conform,","p":"comma"},{"w":"they"},{"w":"are"},{"w":"quickly"},{"w":"labelled"},{"w":"as"},{"w":"difficult.","p":"paragraph"},{"w":"If"},{"w":"they"},{"w":"choose"},{"w":"to"},{"w":"comply,","p":"comma"},{"w":"they"},{"w":"are"},{"w":"forced"},{"w":"into"},{"w":"an"},{"w":"uncomfortable"},{"w":"daily"},{"w":"hypocrisy.","p":"paragraph"},{"w":"Neither"},{"w":"of"},{"w":"these"},{"w":"compromises"},{"w":"offers"},{"w":"a"},{"w":"sustainable"},{"w":"path"},{"w":"forward.","p":"paragraph"},{"w":"The"},{"w":"silence"},{"w":"spreads.","p":"sentence"},{"w":"Other"},{"w":"engineers"},{"w":"notice"},{"w":"who"},{"w":"gets"},{"w":"rewarded"},{"w":"and"},{"w":"who"},{"w":"gets"},{"w":"labelled.","p":"sentence"},{"w":"The"},{"w":"ones"},{"w":"who"},{"w":"speak"},{"w":"in"},{"w":"plans"},{"w":"and"},{"w":"milestones"},{"w":"advance.","p":"sentence"},{"w":"The"},{"w":"ones"},{"w":"who"},{"w":"speak"},{"w":"in"},{"w":"mechanisms"},{"w":"and"},{"w":"failure"},{"w":"modes"},{"w":"are"},{"w":"sidelined.","p":"sentence"},{"w":"The"},{"w":"ones"},{"w":"who"},{"w":"say"},{"w":"“we"},{"w":"can"},{"w":"do"},{"w":"this”"},{"w":"get"},{"w":"promoted.","p":"sentence"},{"w":"The"},{"w":"ones"},{"w":"who"},{"w":"say"},{"w":"“we"},{"w":"cannot"},{"w":"do"},{"w":"this,","p":"comma"},{"w":"but"},{"w":"we"},{"w":"could"},{"w":"do"},{"w":"that"},{"w":"instead”"},{"w":"get"},{"w":"managed.","p":"sentence"},{"w":"The"},{"w":"organisation"},{"w":"selects"},{"w":"for"},{"w":"fluency"},{"w":"in"},{"w":"representation"},{"w":"and"},{"w":"against"},{"w":"fluency"},{"w":"in"},{"w":"reality.","p":"paragraph"},{"w":"Over"},{"w":"time,","p":"comma"},{"w":"two"},{"w":"populations"},{"w":"emerge.","p":"sentence"},{"w":"Those"},{"w":"who"},{"w":"have"},{"w":"adapted"},{"w":"to"},{"w":"the"},{"w":"representation"},{"w":"layer,","p":"comma"},{"w":"who"},{"w":"have"},{"w":"learned"},{"w":"to"},{"w":"speak"},{"w":"in"},{"w":"roadmaps,","p":"comma"},{"w":"OKRs,","p":"comma"},{"w":"alignment"},{"w":"language,","p":"comma"},{"w":"and"},{"w":"strategic"},{"w":"narrative,","p":"comma"},{"w":"and"},{"w":"those"},{"w":"who"},{"w":"have"},{"w":"not.","p":"sentence"},{"w":"The"},{"w":"adapted"},{"w":"population"},{"w":"rises.","p":"sentence"},{"w":"The"},{"w":"unadapted"},{"w":"population"},{"w":"leaves,","p":"comma"},{"w":"disengages,","p":"comma"},{"w":"or"},{"w":"is"},{"w":"pushed"},{"w":"into"},{"w":"increasingly"},{"w":"narrow"},{"w":"technical"},{"w":"roles"},{"w":"where"},{"w":"their"},{"w":"reality-"},{"w":"orientation"},{"w":"cannot"},{"w":"disrupt"},{"w":"the"},{"w":"narrative.","p":"sentence"},{"w":"Senior"},{"w":"engineers"},{"w":"become"},{"w":"“technical"},{"w":"leads”"},{"w":"without"},{"w":"authority.","p":"sentence"},{"w":"Architects"},{"w":"become"},{"w":"diagram"},{"w":"maintainers.","p":"sentence"},{"w":"Staff"},{"w":"engineers"},{"w":"become"},{"w":"firefighters,","p":"comma"},{"w":"called"},{"w":"upon"},{"w":"when"},{"w":"the"},{"w":"system"},{"w":"breaks"},{"w":"but"},{"w":"excluded"},{"w":"from"},{"w":"the"},{"w":"decisions"},{"w":"that"},{"w":"caused"},{"w":"it"},{"w":"to"},{"w":"break.","p":"paragraph"},{"w":"The"},{"w":"organisation"},{"w":"experiences"},{"w":"this"},{"w":"as"},{"w":"a"},{"w":"talent"},{"w":"problem.","p":"sentence"},{"w":"It"},{"w":"is"},{"w":"not.","p":"sentence"},{"w":"It"},{"w":"is"},{"w":"a"},{"w":"selection"},{"w":"problem.","p":"sentence"},{"w":"The"},{"w":"organisation"},{"w":"is"},{"w":"systematically"},{"w":"filtering"},{"w":"out"},{"w":"the"},{"w":"people"},{"w":"it"},{"w":"needs"},{"w":"most.","p":"paragraph"},{"w":"When"},{"w":"reality"},{"w":"is"},{"w":"optional,","p":"comma"},{"w":"the"},{"w":"people"},{"w":"who"},{"w":"insist"},{"w":"on"},{"w":"it"},{"w":"become"},{"w":"inconvenient.","p":"sentence"},{"w":"When"},{"w":"vagueness"},{"w":"is"},{"w":"rewarded,","p":"comma"},{"w":"the"},{"w":"people"},{"w":"who"},{"w":"cannot"},{"w":"produce"},{"w":"it"},{"w":"are"},{"w":"disadvantaged.","p":"sentence"},{"w":"The"},{"w":"surrounding"},{"w":"system"},{"w":"does"},{"w":"not"},{"w":"actively"},{"w":"need"},{"w":"to"},{"w":"be"},{"w":"hostile;","p":"comma"},{"w":"it"},{"w":"merely"},{"w":"needs"},{"w":"to"},{"w":"maintain"},{"w":"a"},{"w":"consistent"},{"w":"indifference"},{"w":"toward"},{"w":"structural"},{"w":"truth.","p":"paragraph"},{"w":"Others"},{"w":"refuse"},{"w":"to"},{"w":"adapt,","p":"comma"},{"w":"choosing"},{"w":"instead"},{"w":"to"},{"w":"maintain"},{"w":"their"},{"w":"blunt"},{"w":"insistence"},{"w":"on"},{"w":"reality.","p":"sentence"},{"w":"They"},{"w":"continue"},{"w":"to"},{"w":"ask"},{"w":"where"},{"w":"the"},{"w":"boundary"},{"w":"is,","p":"comma"},{"w":"where"},{"w":"the"},{"w":"process"},{"w":"is"},{"w":"defined,","p":"comma"},{"w":"and"},{"w":"who"},{"w":"owns"},{"w":"the"},{"w":"outcome.","p":"sentence"},{"w":"They"},{"w":"keep"},{"w":"pointing"},{"w":"at"},{"w":"the"},{"w":"system.","p":"sentence"},{"w":"They"},{"w":"keep"},{"w":"refusing"},{"w":"to"},{"w":"pretend.","p":"sentence"},{"w":"These"},{"w":"people"},{"w":"are"},{"w":"often"},{"w":"labelled"},{"w":"as"},{"w":"negative,","p":"comma"},{"w":"not"},{"w":"team"},{"w":"players,","p":"comma"},{"w":"or"},{"w":"lacking"},{"w":"in"},{"w":"soft"},{"w":"skills.","p":"sentence"},{"w":"They"},{"w":"are"},{"w":"described"},{"w":"as"},{"w":"“good"},{"w":"technically"},{"w":"but"},{"w":"poor"},{"w":"culturally.”"},{"w":"In"},{"w":"reality,","p":"comma"},{"w":"their"},{"w":"behaviour"},{"w":"is"},{"w":"rational.","p":"sentence"},{"w":"The"},{"w":"system"},{"w":"that"},{"w":"punishes"},{"w":"it"},{"w":"is"},{"w":"not.","p":"sentence"},{"w":"Their"},{"w":"cultural"},{"w":"failure"},{"w":"is"},{"w":"a"},{"w":"refusal"},{"w":"to"},{"w":"participate"},{"w":"in"},{"w":"fiction.","p":"paragraph"},{"w":"Eventually,","p":"comma"},{"w":"most"},{"w":"of"},{"w":"these"},{"w":"people"},{"w":"leave,","p":"comma"},{"w":"disengage,","p":"comma"},{"w":"or"},{"w":"become"},{"w":"absorbed"},{"w":"into"},{"w":"the"},{"w":"illusion"},{"w":"machinery.","p":"sentence"},{"w":"None"},{"w":"of"},{"w":"these"},{"w":"outcomes"},{"w":"are"},{"w":"good"},{"w":"for"},{"w":"the"},{"w":"organisation.","p":"sentence"},{"w":"The"},{"w":"knowledge"},{"w":"that"},{"w":"leaves"},{"w":"with"},{"w":"them"},{"w":"is"},{"w":"not"},{"w":"replaceable"},{"w":"through"},{"w":"hiring,","p":"comma"},{"w":"because"},{"w":"the"},{"w":"problem"},{"w":"is"},{"w":"not"},{"w":"a"},{"w":"shortage"},{"w":"of"},{"w":"talent.","p":"sentence"},{"w":"It"},{"w":"is"},{"w":"an"},{"w":"environment"},{"w":"that"},{"w":"makes"},{"w":"talent"},{"w":"irrelevant.","p":"sentence"},{"w":"A"},{"w":"brilliant"},{"w":"engineer"},{"w":"cannot"},{"w":"be"},{"w":"effective"},{"w":"if"},{"w":"the"},{"w":"system"},{"w":"she"},{"w":"works"},{"w":"within"},{"w":"prevents"},{"w":"her"},{"w":"from"},{"w":"seeing"},{"w":"reality,","p":"comma"},{"w":"naming"},{"w":"it,","p":"comma"},{"w":"and"},{"w":"acting"},{"w":"on"},{"w":"it.","p":"paragraph"},{"w":"The"},{"w":"organisation"},{"w":"hires"},{"w":"replacements.","p":"sentence"},{"w":"The"},{"w":"replacements"},{"w":"arrive"},{"w":"without"},{"w":"context,","p":"comma"},{"w":"without"},{"w":"knowledge"},{"w":"of"},{"w":"the"},{"w":"system's"},{"w":"real"},{"w":"behaviour,","p":"comma"},{"w":"without"},{"w":"understanding"},{"w":"of"},{"w":"why"},{"w":"things"},{"w":"were"},{"w":"built"},{"w":"the"},{"w":"way"},{"w":"they"},{"w":"were.","p":"sentence"},{"w":"They"},{"w":"ask"},{"w":"questions.","p":"sentence"},{"w":"If"},{"w":"the"},{"w":"organisation"},{"w":"still"},{"w":"has"},{"w":"people"},{"w":"who"},{"w":"remember"},{"w":"the"},{"w":"answers,","p":"comma"},{"w":"the"},{"w":"knowledge"},{"w":"transfers"},{"w":"slowly"},{"w":"and"},{"w":"partially.","p":"sentence"},{"w":"If"},{"w":"it"},{"w":"does"},{"w":"not,","p":"comma"},{"w":"if"},{"w":"the"},{"w":"people"},{"w":"who"},{"w":"knew"},{"w":"have"},{"w":"already"},{"w":"left,","p":"comma"},{"w":"the"},{"w":"knowledge"},{"w":"is"},{"w":"simply"},{"w":"lost.","p":"sentence"},{"w":"The"},{"w":"organisation"},{"w":"compensates"},{"w":"by"},{"w":"adding"},{"w":"more"},{"w":"process,","p":"comma"},{"w":"more"},{"w":"documentation,","p":"comma"},{"w":"more"},{"w":"handoffs,","p":"comma"},{"w":"more"},{"w":"coordination.","p":"sentence"},{"w":"Each"},{"w":"addition"},{"w":"increases"},{"w":"the"},{"w":"distance"},{"w":"between"},{"w":"the"},{"w":"work"},{"w":"and"},{"w":"the"},{"w":"reality"},{"w":"it"},{"w":"is"},{"w":"supposed"},{"w":"to"},{"w":"address.","p":"paragraph"},{"w":"The"},{"w":"organisation"},{"w":"incorrectly"},{"w":"perceives"},{"w":"a"},{"w":"talent"},{"w":"problem"},{"w":"when"},{"w":"it"},{"w":"actually"},{"w":"suffers"},{"w":"from"},{"w":"a"},{"w":"fundamental"},{"w":"inability"},{"w":"to"},{"w":"confront"},{"w":"truth.","p":"paragraph"},{"w":"How"},{"w":"People"},{"w":"Cope","p":"heading"}]