[{"w":"Customer"},{"w":"Journeys"},{"w":"Are"},{"w":"Business"},{"w":"Processes","p":"heading"},{"w":"If"},{"w":"you"},{"w":"recognised"},{"w":"the"},{"w":"patterns"},{"w":"described"},{"w":"in"},{"w":"the"},{"w":"previous"},{"w":"chapters—the"},{"w":"fake"},{"w":"products,","p":"comma"},{"w":"the"},{"w":"avoidant"},{"w":"architectures,","p":"comma"},{"w":"and"},{"w":"the"},{"w":"simulated"},{"w":"autonomy—the"},{"w":"structure"},{"w":"produced"},{"w":"them,","p":"comma"},{"w":"not"},{"w":"the"},{"w":"people"},{"w":"inside"},{"w":"it.","p":"sentence"},{"w":"What"},{"w":"follows"},{"w":"describes"},{"w":"what"},{"w":"changes"},{"w":"when"},{"w":"the"},{"w":"organisation"},{"w":"stops"},{"w":"avoiding"},{"w":"reality.","p":"paragraph"},{"w":"A"},{"w":"retail"},{"w":"bank"},{"w":"decides"},{"w":"to"},{"w":"map"},{"w":"its"},{"w":"mortgage"},{"w":"origination"},{"w":"process.","p":"sentence"},{"w":"Three"},{"w":"departments"},{"w":"are"},{"w":"involved:","p":"comma"},{"w":"the"},{"w":"digital"},{"w":"team"},{"w":"that"},{"w":"owns"},{"w":"the"},{"w":"online"},{"w":"application,","p":"comma"},{"w":"the"},{"w":"credit"},{"w":"risk"},{"w":"team"},{"w":"that"},{"w":"owns"},{"w":"the"},{"w":"decisioning,","p":"comma"},{"w":"and"},{"w":"the"},{"w":"operations"},{"w":"team"},{"w":"that"},{"w":"handles"},{"w":"document"},{"w":"verification"},{"w":"and"},{"w":"disbursement.","p":"paragraph"},{"w":"A"},{"w":"workshop"},{"w":"is"},{"w":"convened.","p":"sentence"},{"w":"Within"},{"w":"twenty"},{"w":"minutes,","p":"comma"},{"w":"it"},{"w":"becomes"},{"w":"clear"},{"w":"that"},{"w":"the"},{"w":"three"},{"w":"departments"},{"w":"are"},{"w":"describing"},{"w":"different"},{"w":"processes.","p":"paragraph"},{"w":"The"},{"w":"digital"},{"w":"team"},{"w":"presents"},{"w":"the"},{"w":"customer"},{"w":"journey:","p":"comma"},{"w":"a"},{"w":"user"},{"w":"fills"},{"w":"in"},{"w":"an"},{"w":"application"},{"w":"form,","p":"comma"},{"w":"uploads"},{"w":"documents,","p":"comma"},{"w":"receives"},{"w":"a"},{"w":"provisional"},{"w":"offer,","p":"comma"},{"w":"accepts,","p":"comma"},{"w":"and"},{"w":"receives"},{"w":"funds.","p":"sentence"},{"w":"They"},{"w":"have"},{"w":"analytics.","p":"sentence"},{"w":"They"},{"w":"know"},{"w":"where"},{"w":"users"},{"w":"drop"},{"w":"off.","p":"sentence"},{"w":"They"},{"w":"have"},{"w":"optimised"},{"w":"the"},{"w":"funnel.","p":"paragraph"},{"w":"The"},{"w":"credit"},{"w":"risk"},{"w":"team"},{"w":"presents"},{"w":"a"},{"w":"decisioning"},{"w":"flow:","p":"comma"},{"w":"application"},{"w":"data"},{"w":"is"},{"w":"ingested,","p":"comma"},{"w":"scored"},{"w":"against"},{"w":"a"},{"w":"model,","p":"comma"},{"w":"reviewed"},{"w":"by"},{"w":"an"},{"w":"analyst"},{"w":"if"},{"w":"the"},{"w":"score"},{"w":"is"},{"w":"marginal,","p":"comma"},{"w":"and"},{"w":"either"},{"w":"approved"},{"w":"or"},{"w":"declined.","p":"sentence"},{"w":"They"},{"w":"have"},{"w":"SLAs.","p":"sentence"},{"w":"They"},{"w":"have"},{"w":"audit"},{"w":"requirements.","p":"sentence"},{"w":"They"},{"w":"have"},{"w":"a"},{"w":"regulatory"},{"w":"obligation"},{"w":"to"},{"w":"explain"},{"w":"every"},{"w":"decision.","p":"paragraph"},{"w":"The"},{"w":"operations"},{"w":"team"},{"w":"presents"},{"w":"a"},{"w":"fulfilment"},{"w":"process:","p":"comma"},{"w":"verified"},{"w":"documents"},{"w":"are"},{"w":"matched"},{"w":"to"},{"w":"approved"},{"w":"applications,","p":"comma"},{"w":"compliance"},{"w":"checks"},{"w":"are"},{"w":"run,","p":"comma"},{"w":"funds"},{"w":"are"},{"w":"released"},{"w":"to"},{"w":"the"},{"w":"notary,","p":"comma"},{"w":"and"},{"w":"the"},{"w":"mortgage"},{"w":"is"},{"w":"registered.","p":"sentence"},{"w":"They"},{"w":"have"},{"w":"checklists.","p":"sentence"},{"w":"They"},{"w":"have"},{"w":"exception"},{"w":"queues.","p":"sentence"},{"w":"They"},{"w":"have"},{"w":"a"},{"w":"backlog"},{"w":"of"},{"w":"applications"},{"w":"that"},{"w":"are"},{"w":"“stuck”"},{"w":"for"},{"w":"reasons"},{"w":"no"},{"w":"system"},{"w":"tracks.","p":"paragraph"},{"w":"Each"},{"w":"team's"},{"w":"description"},{"w":"is"},{"w":"internally"},{"w":"coherent.","p":"sentence"},{"w":"None"},{"w":"of"},{"w":"them"},{"w":"connect.","p":"sentence"},{"w":"The"},{"w":"digital"},{"w":"team"},{"w":"does"},{"w":"not"},{"w":"know"},{"w":"what"},{"w":"happens"},{"w":"between"},{"w":"“provisional"},{"w":"offer”"},{"w":"and"},{"w":"“funds"},{"w":"received.”"},{"w":"The"},{"w":"credit"},{"w":"risk"},{"w":"team"},{"w":"does"},{"w":"not"},{"w":"know"},{"w":"what"},{"w":"the"},{"w":"customer"},{"w":"experiences"},{"w":"during"},{"w":"the"},{"w":"decisioning"},{"w":"window.","p":"sentence"},{"w":"The"},{"w":"operations"},{"w":"team"},{"w":"does"},{"w":"not"},{"w":"know"},{"w":"why"},{"w":"certain"},{"w":"applications"},{"w":"arrive"},{"w":"with"},{"w":"missing"},{"w":"documents,","p":"comma"},{"w":"because"},{"w":"the"},{"w":"upstream"},{"w":"systems"},{"w":"do"},{"w":"not"},{"w":"enforce"},{"w":"completeness.","p":"paragraph"},{"w":"The"},{"w":"workshop"},{"w":"is"},{"w":"meant"},{"w":"to"},{"w":"last"},{"w":"two"},{"w":"hours.","p":"sentence"},{"w":"It"},{"w":"runs"},{"w":"for"},{"w":"four.","p":"sentence"},{"w":"At"},{"w":"the"},{"w":"end,","p":"comma"},{"w":"the"},{"w":"facilitator"},{"w":"produces"},{"w":"a"},{"w":"diagram"},{"w":"that"},{"w":"connects"},{"w":"the"},{"w":"three"},{"w":"views.","p":"sentence"},{"w":"Everyone"},{"w":"agrees"},{"w":"it"},{"w":"is"},{"w":"useful.","p":"sentence"},{"w":"The"},{"w":"diagram"},{"w":"is"},{"w":"saved"},{"w":"to"},{"w":"a"},{"w":"shared"},{"w":"drive.","p":"sentence"},{"w":"It"},{"w":"operates"},{"w":"independently"},{"w":"of"},{"w":"any"},{"w":"underlying"},{"w":"system"},{"w":"and"},{"w":"entirely"},{"w":"lacks"},{"w":"formal"},{"w":"versioning.","p":"sentence"},{"w":"It"},{"w":"is"},{"w":"not"},{"w":"updated"},{"w":"when"},{"w":"the"},{"w":"digital"},{"w":"team"},{"w":"redesigns"},{"w":"the"},{"w":"application"},{"w":"form"},{"w":"six"},{"w":"months"},{"w":"later.","p":"paragraph"},{"w":"When"},{"w":"the"},{"w":"redesigned"},{"w":"form"},{"w":"collects"},{"w":"data"},{"w":"in"},{"w":"a"},{"w":"format"},{"w":"the"},{"w":"scoring"},{"w":"model"},{"w":"cannot"},{"w":"ingest,","p":"comma"},{"w":"a"},{"w":"manual"},{"w":"workaround"},{"w":"is"},{"w":"created.","p":"sentence"},{"w":"The"},{"w":"workaround"},{"w":"introduces"},{"w":"a"},{"w":"two-"},{"w":"day"},{"w":"delay.","p":"sentence"},{"w":"Customer"},{"w":"complaints"},{"w":"increase.","p":"sentence"},{"w":"The"},{"w":"delay"},{"w":"is"},{"w":"attributed"},{"w":"to"},{"w":"“operations.”","p":"paragraph"},{"w":"The"},{"w":"diagram"},{"w":"is"},{"w":"neither"},{"w":"actively"},{"w":"consulted"},{"w":"nor"},{"w":"deliberately"},{"w":"maintained"},{"w":"within"},{"w":"the"},{"w":"team's"},{"w":"working"},{"w":"memory.","p":"separator"},{"w":"One"},{"w":"of"},{"w":"the"},{"w":"most"},{"w":"persistent"},{"w":"sources"},{"w":"of"},{"w":"confusion"},{"w":"in"},{"w":"software-"},{"w":"dependent"},{"w":"corporates"},{"w":"is"},{"w":"the"},{"w":"belief"},{"w":"that"},{"w":"business"},{"w":"processes"},{"w":"and"},{"w":"customer"},{"w":"journeys"},{"w":"are"},{"w":"fundamentally"},{"w":"different"},{"w":"concerns,","p":"comma"},{"w":"owned"},{"w":"by"},{"w":"different"},{"w":"functions,","p":"comma"},{"w":"expressed"},{"w":"in"},{"w":"different"},{"w":"languages,","p":"comma"},{"w":"and"},{"w":"reconciled"},{"w":"only"},{"w":"when"},{"w":"a"},{"w":"problem"},{"w":"makes"},{"w":"the"},{"w":"disconnection"},{"w":"visible.","p":"paragraph"},{"w":"They"},{"w":"do"},{"w":"not"},{"w":"represent"},{"w":"isolated"},{"w":"concerns.","p":"paragraph"},{"w":"Rather,","p":"comma"},{"w":"they"},{"w":"function"},{"w":"as"},{"w":"two"},{"w":"distinct"},{"w":"perspectives"},{"w":"on"},{"w":"the"},{"w":"same"},{"w":"underlying"},{"w":"structure.","p":"paragraph"},{"w":"A"},{"w":"customer"},{"w":"journey"},{"w":"is"},{"w":"an"},{"w":"outside-"},{"w":"in"},{"w":"view"},{"w":"of"},{"w":"how"},{"w":"value"},{"w":"is"},{"w":"experienced.","p":"sentence"},{"w":"It"},{"w":"describes"},{"w":"the"},{"w":"sequence"},{"w":"of"},{"w":"interactions"},{"w":"through"},{"w":"which"},{"w":"a"},{"w":"person"},{"w":"achieves"},{"w":"something"},{"w":"meaningful:","p":"comma"},{"w":"apply"},{"w":"for"},{"w":"a"},{"w":"mortgage,","p":"comma"},{"w":"file"},{"w":"a"},{"w":"claim,","p":"comma"},{"w":"renew"},{"w":"a"},{"w":"policy,","p":"comma"},{"w":"return"},{"w":"a"},{"w":"product.","p":"sentence"},{"w":"It"},{"w":"emphasises"},{"w":"intent,","p":"comma"},{"w":"friction,","p":"comma"},{"w":"and"},{"w":"outcome.","p":"paragraph"},{"w":"A"},{"w":"business"},{"w":"process"},{"w":"is"},{"w":"an"},{"w":"inside-"},{"w":"out"},{"w":"view"},{"w":"of"},{"w":"how"},{"w":"that"},{"w":"same"},{"w":"value"},{"w":"is"},{"w":"produced.","p":"sentence"},{"w":"It"},{"w":"describes"},{"w":"the"},{"w":"activities,","p":"comma"},{"w":"decisions,","p":"comma"},{"w":"and"},{"w":"state"},{"w":"transitions"},{"w":"required"},{"w":"to"},{"w":"fulfil"},{"w":"that"},{"w":"intent:","p":"comma"},{"w":"receive"},{"w":"an"},{"w":"application,","p":"comma"},{"w":"check"},{"w":"completeness,","p":"comma"},{"w":"assess"},{"w":"creditworthiness,","p":"comma"},{"w":"generate"},{"w":"an"},{"w":"offer,","p":"comma"},{"w":"verify"},{"w":"documents,","p":"comma"},{"w":"disburse"},{"w":"funds.","p":"sentence"},{"w":"It"},{"w":"emphasises"},{"w":"responsibility,","p":"comma"},{"w":"constraints,","p":"comma"},{"w":"execution,","p":"comma"},{"w":"and"},{"w":"failure"},{"w":"modes.","p":"paragraph"},{"w":"In"},{"w":"essence,","p":"comma"},{"w":"they"},{"w":"describe"},{"w":"the"},{"w":"same"},{"w":"mechanism"},{"w":"observed"},{"w":"from"},{"w":"opposite"},{"w":"sides"},{"w":"of"},{"w":"the"},{"w":"process"},{"w":"boundary.","p":"paragraph"},{"w":"A"},{"w":"mortgage"},{"w":"application"},{"w":"journey"},{"w":"and"},{"w":"a"},{"w":"mortgage"},{"w":"origination"},{"w":"process"},{"w":"describe"},{"w":"the"},{"w":"same"},{"w":"work.","p":"sentence"},{"w":"One"},{"w":"describes"},{"w":"it"},{"w":"from"},{"w":"the"},{"w":"applicant's"},{"w":"perspective;","p":"comma"},{"w":"the"},{"w":"other"},{"w":"from"},{"w":"the"},{"w":"organisation's"},{"w":"perspective.","p":"sentence"},{"w":"If"},{"w":"they"},{"w":"are"},{"w":"not"},{"w":"reconciled,","p":"comma"},{"w":"the"},{"w":"applicant"},{"w":"feels"},{"w":"one"},{"w":"reality"},{"w":"while"},{"w":"the"},{"w":"organisation"},{"w":"thinks"},{"w":"it"},{"w":"delivered"},{"w":"another.","p":"sentence"},{"w":"The"},{"w":"gap"},{"w":"between"},{"w":"them"},{"w":"is"},{"w":"where"},{"w":"value"},{"w":"is"},{"w":"destroyed,","p":"comma"},{"w":"complaints"},{"w":"appear,","p":"comma"},{"w":"and"},{"w":"trust"},{"w":"erodes.","p":"paragraph"},{"w":"The"},{"w":"distinction"},{"w":"only"},{"w":"becomes"},{"w":"problematic"},{"w":"when"},{"w":"an"},{"w":"organisation"},{"w":"treats"},{"w":"one"},{"w":"as"},{"w":"primary"},{"w":"and"},{"w":"the"},{"w":"other"},{"w":"as"},{"w":"optional.","p":"paragraph"},{"w":"In"},{"w":"software-"},{"w":"dependent"},{"w":"corporates,","p":"comma"},{"w":"customer"},{"w":"journeys"},{"w":"are"},{"w":"often"},{"w":"treated"},{"w":"as"},{"w":"aspirational"},{"w":"artefacts:","p":"comma"},{"w":"high-"},{"w":"level"},{"w":"narratives"},{"w":"that"},{"w":"are"},{"w":"stripped"},{"w":"of"},{"w":"operational"},{"w":"detail"},{"w":"and"},{"w":"designed"},{"w":"to"},{"w":"inspire"},{"w":"rather"},{"w":"than"},{"w":"constrain.","p":"sentence"},{"w":"They"},{"w":"live"},{"w":"in"},{"w":"decks"},{"w":"prepared"},{"w":"by"},{"w":"design"},{"w":"teams"},{"w":"or"},{"w":"strategy"},{"w":"consultants,","p":"comma"},{"w":"shown"},{"w":"at"},{"w":"offsites"},{"w":"and"},{"w":"taped"},{"w":"to"},{"w":"walls.","p":"sentence"},{"w":"They"},{"w":"describe"},{"w":"what"},{"w":"the"},{"w":"organisation"},{"w":"wished"},{"w":"the"},{"w":"customer"},{"w":"experienced.","p":"paragraph"},{"w":"Business"},{"w":"processes,","p":"comma"},{"w":"where"},{"w":"they"},{"w":"exist"},{"w":"at"},{"w":"all,","p":"comma"},{"w":"are"},{"w":"often"},{"w":"treated"},{"w":"as"},{"w":"internal"},{"w":"plumbing:","p":"comma"},{"w":"documented"},{"w":"only"},{"w":"for"},{"w":"compliance"},{"w":"or"},{"w":"audit"},{"w":"purposes,","p":"comma"},{"w":"and"},{"w":"then"},{"w":"only"},{"w":"perfunctorily.","p":"sentence"},{"w":"They"},{"w":"live"},{"w":"in"},{"w":"process"},{"w":"registers"},{"w":"maintained"},{"w":"by"},{"w":"quality"},{"w":"teams.","p":"sentence"},{"w":"They"},{"w":"describe"},{"w":"what"},{"w":"the"},{"w":"organisation"},{"w":"is"},{"w":"obligated"},{"w":"to"},{"w":"do"},{"w":"for"},{"w":"regulators,","p":"comma"},{"w":"not"},{"w":"what"},{"w":"it"},{"w":"actually"},{"w":"does"},{"w":"for"},{"w":"customers.","p":"paragraph"},{"w":"Neither"},{"w":"framework"},{"w":"ultimately"},{"w":"governs"},{"w":"the"},{"w":"system's"},{"w":"operational"},{"w":"behaviour.","p":"paragraph"},{"w":"This"},{"w":"artificial"},{"w":"separation"},{"w":"imposes"},{"w":"severe"},{"w":"operational"},{"w":"consequences.","p":"paragraph"},{"w":"When"},{"w":"journeys"},{"w":"are"},{"w":"vague,","p":"comma"},{"w":"engineers"},{"w":"are"},{"w":"asked"},{"w":"to"},{"w":"build"},{"w":"systems"},{"w":"without"},{"w":"a"},{"w":"clear"},{"w":"definition"},{"w":"of"},{"w":"success.","p":"sentence"},{"w":"What"},{"w":"does"},{"w":"it"},{"w":"mean"},{"w":"to"},{"w":"“improve"},{"w":"the"},{"w":"onboarding"},{"w":"experience”?","p":"sentence"},{"w":"Without"},{"w":"a"},{"w":"precise"},{"w":"journey"},{"w":"that"},{"w":"specifies"},{"w":"what"},{"w":"the"},{"w":"user"},{"w":"does"},{"w":"at"},{"w":"each"},{"w":"step"},{"w":"and"},{"w":"what"},{"w":"the"},{"w":"system"},{"w":"does"},{"w":"in"},{"w":"response,","p":"comma"},{"w":"the"},{"w":"instruction"},{"w":"is"},{"w":"under-"},{"w":"specified"},{"w":"and"},{"w":"will"},{"w":"be"},{"w":"interpreted"},{"w":"in"},{"w":"multiple"},{"w":"ways.","p":"paragraph"},{"w":"When"},{"w":"processes"},{"w":"are"},{"w":"implicit,","p":"comma"},{"w":"ownership"},{"w":"is"},{"w":"unclear"},{"w":"and"},{"w":"accountability"},{"w":"diffuses.","p":"sentence"},{"w":"Which"},{"w":"team"},{"w":"is"},{"w":"responsible"},{"w":"when"},{"w":"a"},{"w":"mortgage"},{"w":"application"},{"w":"gets"},{"w":"stuck"},{"w":"between"},{"w":"decisioning"},{"w":"and"},{"w":"document"},{"w":"verification?","p":"sentence"},{"w":"Without"},{"w":"an"},{"w":"explicit"},{"w":"process"},{"w":"that"},{"w":"assigns"},{"w":"ownership"},{"w":"to"},{"w":"each"},{"w":"transition,","p":"comma"},{"w":"the"},{"w":"answer"},{"w":"is:","p":"comma"},{"w":"nobody.","p":"sentence"},{"w":"The"},{"w":"application"},{"w":"enters"},{"w":"a"},{"w":"queue"},{"w":"that"},{"w":"no"},{"w":"system"},{"w":"monitors.","p":"sentence"},{"w":"The"},{"w":"customer"},{"w":"calls,","p":"comma"},{"w":"and"},{"w":"customer"},{"w":"service"},{"w":"has"},{"w":"no"},{"w":"answer"},{"w":"because"},{"w":"the"},{"w":"process"},{"w":"was"},{"w":"never"},{"w":"written"},{"w":"down.","p":"paragraph"},{"w":"When"},{"w":"journeys"},{"w":"and"},{"w":"processes"},{"w":"are"},{"w":"not"},{"w":"reconciled,","p":"comma"},{"w":"the"},{"w":"organisation"},{"w":"cannot"},{"w":"reason"},{"w":"end-"},{"w":"to-"},{"w":"end"},{"w":"about"},{"w":"how"},{"w":"value"},{"w":"is"},{"w":"created"},{"w":"or"},{"w":"destroyed.","p":"sentence"},{"w":"Instead,","p":"comma"},{"w":"it"},{"w":"is"},{"w":"forced"},{"w":"to"},{"w":"reason"},{"w":"in"},{"w":"disconnected"},{"w":"fragments.","p":"paragraph"},{"w":"Product"},{"w":"teams"},{"w":"talk"},{"w":"about"},{"w":"experience.","p":"sentence"},{"w":"Operations"},{"w":"teams"},{"w":"talk"},{"w":"about"},{"w":"throughput.","p":"sentence"},{"w":"Finance"},{"w":"talks"},{"w":"about"},{"w":"cost.","p":"sentence"},{"w":"Architecture"},{"w":"talks"},{"w":"about"},{"w":"systems.","p":"sentence"},{"w":"Each"},{"w":"view"},{"w":"is"},{"w":"locally"},{"w":"coherent,","p":"comma"},{"w":"but"},{"w":"none"},{"w":"of"},{"w":"them"},{"w":"align.","p":"sentence"},{"w":"When"},{"w":"alignment"},{"w":"is"},{"w":"attempted,","p":"comma"},{"w":"it"},{"w":"is"},{"w":"performed"},{"w":"through"},{"w":"translation"},{"w":"layers:","p":"comma"},{"w":"meetings,","p":"comma"},{"w":"intermediaries,","p":"comma"},{"w":"and"},{"w":"documents"},{"w":"that"},{"w":"describe"},{"w":"what"},{"w":"everyone"},{"w":"hopes"},{"w":"is"},{"w":"true.","p":"sentence"},{"w":"It"},{"w":"is"},{"w":"not"},{"w":"performed"},{"w":"through"},{"w":"shared"},{"w":"artefacts"},{"w":"that"},{"w":"bind.","p":"paragraph"},{"w":"The"},{"w":"organisation"},{"w":"compensates"},{"w":"by"},{"w":"inventing"},{"w":"intermediaries.","p":"sentence"},{"w":"Product"},{"w":"managers"},{"w":"translate"},{"w":"journeys"},{"w":"into"},{"w":"backlogs.","p":"sentence"},{"w":"Architects"},{"w":"translate"},{"w":"intent"},{"w":"into"},{"w":"diagrams.","p":"sentence"},{"w":"Programme"},{"w":"managers"},{"w":"translate"},{"w":"dependencies"},{"w":"into"},{"w":"plans.","p":"sentence"},{"w":"Business"},{"w":"analysts"},{"w":"translate"},{"w":"requirements"},{"w":"into"},{"w":"specifications.","p":"sentence"},{"w":"None"},{"w":"of"},{"w":"these"},{"w":"translations"},{"w":"are"},{"w":"authoritative,","p":"comma"},{"w":"because"},{"w":"the"},{"w":"underlying"},{"w":"structure"},{"w":"has"},{"w":"never"},{"w":"been"},{"w":"made"},{"w":"explicit"},{"w":"enough"},{"w":"to"},{"w":"contradict"},{"w":"a"},{"w":"narrative.","p":"sentence"},{"w":"Each"},{"w":"translation"},{"w":"introduces"},{"w":"drift.","p":"sentence"},{"w":"Over"},{"w":"time,","p":"comma"},{"w":"they"},{"w":"diverge"},{"w":"from"},{"w":"each"},{"w":"other"},{"w":"and"},{"w":"from"},{"w":"the"},{"w":"system,","p":"comma"},{"w":"and"},{"w":"no"},{"w":"one"},{"w":"can"},{"w":"tell"},{"w":"which"},{"w":"version"},{"w":"is"},{"w":"current"},{"w":"because"},{"w":"none"},{"w":"of"},{"w":"them"},{"w":"were"},{"w":"ever"},{"w":"real.","p":"paragraph"},{"w":"This"},{"w":"is"},{"w":"why"},{"w":"so"},{"w":"many"},{"w":"initiatives"},{"w":"fail"},{"w":"in"},{"w":"ways"},{"w":"that"},{"w":"are"},{"w":"difficult"},{"w":"to"},{"w":"explain"},{"w":"after"},{"w":"the"},{"w":"fact.","p":"sentence"},{"w":"Artefacts"},{"w":"can"},{"w":"look"},{"w":"reasonable"},{"w":"in"},{"w":"isolation.","p":"sentence"},{"w":"No"},{"w":"one"},{"w":"can"},{"w":"explain"},{"w":"how"},{"w":"they"},{"w":"were"},{"w":"meant"},{"w":"to"},{"w":"work"},{"w":"together.","p":"sentence"},{"w":"When"},{"w":"the"},{"w":"customer"},{"w":"experiences"},{"w":"failure—a"},{"w":"delayed"},{"w":"application,","p":"comma"},{"w":"a"},{"w":"lost"},{"w":"claim,","p":"comma"},{"w":"a"},{"w":"renewal"},{"w":"with"},{"w":"the"},{"w":"wrong"},{"w":"premium—it"},{"w":"appears"},{"w":"as"},{"w":"poor"},{"w":"execution"},{"w":"rather"},{"w":"than"},{"w":"structural"},{"w":"incoherence.","p":"sentence"},{"w":"The"},{"w":"customer"},{"w":"blames"},{"w":"the"},{"w":"company.","p":"sentence"},{"w":"The"},{"w":"company"},{"w":"blames"},{"w":"a"},{"w":"team.","p":"sentence"},{"w":"The"},{"w":"team"},{"w":"blames"},{"w":"the"},{"w":"process.","p":"sentence"},{"w":"The"},{"w":"process"},{"w":"does"},{"w":"not"},{"w":"exist.","p":"paragraph"},{"w":"For"},{"w":"those"},{"w":"who"},{"w":"must"},{"w":"operate"},{"w":"within"},{"w":"these"},{"w":"processes,","p":"comma"},{"w":"the"},{"w":"absence"},{"w":"of"},{"w":"explicitness"},{"w":"is"},{"w":"immediately"},{"w":"obvious.","p":"sentence"},{"w":"They"},{"w":"are"},{"w":"asked"},{"w":"questions"},{"w":"they"},{"w":"cannot"},{"w":"answer"},{"w":"honestly:","p":"paragraph"},{"w":"What"},{"w":"happens"},{"w":"when"},{"w":"this"},{"w":"user"},{"w":"takes"},{"w":"this"},{"w":"action?","p":"sentence"},{"w":"“It"},{"w":"depends,”"},{"w":"people"},{"w":"reply:","p":"comma"},{"w":"on"},{"w":"which"},{"w":"version"},{"w":"of"},{"w":"the"},{"w":"form"},{"w":"they"},{"w":"used,","p":"comma"},{"w":"whether"},{"w":"the"},{"w":"upstream"},{"w":"system"},{"w":"completed"},{"w":"its"},{"w":"check,","p":"comma"},{"w":"and"},{"w":"whether"},{"w":"the"},{"w":"data"},{"w":"arrived"},{"w":"in"},{"w":"the"},{"w":"right"},{"w":"format.","p":"paragraph"},{"w":"Who"},{"w":"owns"},{"w":"the"},{"w":"outcome"},{"w":"if"},{"w":"something"},{"w":"goes"},{"w":"wrong?","p":"sentence"},{"w":"“We"},{"w":"all"},{"w":"do,”"},{"w":"which"},{"w":"means"},{"w":"nobody"},{"w":"does.","p":"paragraph"},{"w":"Because"},{"w":"the"},{"w":"failure"},{"w":"mode"},{"w":"remains"},{"w":"undefined,","p":"comma"},{"w":"its"},{"w":"occurrence"},{"w":"is"},{"w":"met"},{"w":"only"},{"w":"with"},{"w":"structural"},{"w":"silence.","p":"paragraph"},{"w":"In"},{"w":"organisations"},{"w":"that"},{"w":"have"},{"w":"not"},{"w":"written"},{"w":"these"},{"w":"things"},{"w":"down,","p":"comma"},{"w":"the"},{"w":"answers"},{"w":"are"},{"w":"social"},{"w":"rather"},{"w":"than"},{"w":"structural.","p":"sentence"},{"w":"Ownership"},{"w":"is"},{"w":"inferred"},{"w":"from"},{"w":"history.","p":"sentence"},{"w":"Responsibility"},{"w":"is"},{"w":"negotiated"},{"w":"in"},{"w":"real"},{"w":"time.","p":"sentence"},{"w":"Knowledge"},{"w":"lives"},{"w":"in"},{"w":"people's"},{"w":"heads.","p":"sentence"},{"w":"Change"},{"w":"becomes"},{"w":"risky"},{"w":"because"},{"w":"it"},{"w":"threatens"},{"w":"undocumented"},{"w":"assumptions"},{"w":"that"},{"w":"nobody"},{"w":"can"},{"w":"enumerate.","p":"sentence"},{"w":"The"},{"w":"organisation"},{"w":"is"},{"w":"held"},{"w":"together"},{"w":"by"},{"w":"the"},{"w":"accumulated"},{"w":"context"},{"w":"of"},{"w":"its"},{"w":"longest-"},{"w":"serving"},{"w":"employees,","p":"comma"},{"w":"and"},{"w":"when"},{"w":"they"},{"w":"leave,","p":"comma"},{"w":"that"},{"w":"context"},{"w":"leaves"},{"w":"with"},{"w":"them.","p":"paragraph"},{"w":"This"},{"w":"disconnect"},{"w":"represents"},{"w":"a"},{"w":"fundamental"},{"w":"failure"},{"w":"of"},{"w":"modelling"},{"w":"rather"},{"w":"than"},{"w":"a"},{"w":"mere"},{"w":"lapse"},{"w":"in"},{"w":"documentation.","p":"paragraph"},{"w":"Formally"},{"w":"documenting"},{"w":"a"},{"w":"process"},{"w":"constitutes"},{"w":"an"},{"w":"act"},{"w":"of"},{"w":"structural"},{"w":"commitment,","p":"comma"},{"w":"far"},{"w":"exceeding"},{"w":"a"},{"w":"simple"},{"w":"clerical"},{"w":"exercise.","p":"sentence"},{"w":"It"},{"w":"forces"},{"w":"the"},{"w":"organisation"},{"w":"to"},{"w":"decide"},{"w":"what"},{"w":"it"},{"w":"does,","p":"comma"},{"w":"who"},{"w":"does"},{"w":"it,","p":"comma"},{"w":"and"},{"w":"how"},{"w":"success"},{"w":"and"},{"w":"failure"},{"w":"are"},{"w":"recognised.","p":"sentence"},{"w":"It"},{"w":"collapses"},{"w":"ambiguity.","p":"sentence"},{"w":"It"},{"w":"requires"},{"w":"people"},{"w":"who"},{"w":"may"},{"w":"have"},{"w":"been"},{"w":"peacefully"},{"w":"coexisting"},{"w":"with"},{"w":"incompatible"},{"w":"assumptions"},{"w":"to"},{"w":"confront"},{"w":"those"},{"w":"assumptions"},{"w":"and"},{"w":"resolve"},{"w":"them.","p":"paragraph"},{"w":"This"},{"w":"is"},{"w":"precisely"},{"w":"why"},{"w":"it"},{"w":"is"},{"w":"resisted.","p":"sentence"},{"w":"The"},{"w":"resistance"},{"w":"is"},{"w":"not"},{"w":"always"},{"w":"cynical.","p":"sentence"},{"w":"Some"},{"w":"of"},{"w":"it"},{"w":"comes"},{"w":"from"},{"w":"people"},{"w":"who"},{"w":"have"},{"w":"been"},{"w":"holding"},{"w":"the"},{"w":"process"},{"w":"together"},{"w":"informally"},{"w":"and"},{"w":"who"},{"w":"fear,","p":"comma"},{"w":"with"},{"w":"good"},{"w":"reason,","p":"comma"},{"w":"that"},{"w":"formalising"},{"w":"it"},{"w":"will"},{"w":"expose"},{"w":"its"},{"w":"fragility,","p":"comma"},{"w":"and"},{"w":"that"},{"w":"they"},{"w":"will"},{"w":"be"},{"w":"blamed"},{"w":"for"},{"w":"that"},{"w":"fragility"},{"w":"rather"},{"w":"than"},{"w":"credited"},{"w":"for"},{"w":"the"},{"w":"coping.","p":"sentence"},{"w":"Explicitness"},{"w":"can"},{"w":"feel"},{"w":"punitive"},{"w":"to"},{"w":"the"},{"w":"very"},{"w":"people"},{"w":"who"},{"w":"have"},{"w":"been"},{"w":"compensating"},{"w":"the"},{"w":"hardest.","p":"sentence"},{"w":"The"},{"w":"alternative—leaving"},{"w":"the"},{"w":"process"},{"w":"implicit,","p":"comma"},{"w":"carried"},{"w":"in"},{"w":"people's"},{"w":"heads,","p":"comma"},{"w":"and"},{"w":"dependent"},{"w":"on"},{"w":"continued"},{"w":"presence"},{"w":"and"},{"w":"goodwill—is"},{"w":"not"},{"w":"protection.","p":"sentence"},{"w":"It"},{"w":"is"},{"w":"a"},{"w":"different"},{"w":"kind"},{"w":"of"},{"w":"fragility,","p":"comma"},{"w":"one"},{"w":"that"},{"w":"the"},{"w":"organisation"},{"w":"does"},{"w":"not"},{"w":"notice"},{"w":"until"},{"w":"someone"},{"w":"leaves.","p":"sentence"},{"w":"Explicit"},{"w":"processes"},{"w":"say:","p":"comma"},{"w":"this"},{"w":"is"},{"w":"what"},{"w":"we"},{"w":"do,","p":"comma"},{"w":"this"},{"w":"is"},{"w":"who"},{"w":"is"},{"w":"responsible,","p":"comma"},{"w":"and"},{"w":"this"},{"w":"is"},{"w":"what"},{"w":"failure"},{"w":"looks"},{"w":"like.","p":"sentence"},{"w":"Every"},{"w":"one"},{"w":"of"},{"w":"those"},{"w":"statements"},{"w":"creates"},{"w":"accountability"},{"w":"that"},{"w":"someone"},{"w":"would"},{"w":"prefer"},{"w":"not"},{"w":"to"},{"w":"have.","p":"paragraph"},{"w":"The"},{"w":"cost"},{"w":"of"},{"w":"this"},{"w":"refusal"},{"w":"extends"},{"w":"beyond"},{"w":"the"},{"w":"organisational"},{"w":"chart.","p":"sentence"},{"w":"When"},{"w":"customer"},{"w":"journeys"},{"w":"and"},{"w":"business"},{"w":"processes"},{"w":"are"},{"w":"not"},{"w":"unified"},{"w":"and"},{"w":"explicit,","p":"comma"},{"w":"they"},{"w":"cannot"},{"w":"be"},{"w":"used"},{"w":"to"},{"w":"design"},{"w":"systems.","p":"sentence"},{"w":"Engineers"},{"w":"build"},{"w":"features"},{"w":"against"},{"w":"requirements"},{"w":"that"},{"w":"describe"},{"w":"fragments"},{"w":"of"},{"w":"journeys"},{"w":"and"},{"w":"fragments"},{"w":"of"},{"w":"processes,","p":"comma"},{"w":"without"},{"w":"a"},{"w":"model"},{"w":"that"},{"w":"connects"},{"w":"the"},{"w":"two.","p":"sentence"},{"w":"Architecture"},{"w":"is"},{"w":"then"},{"w":"designed"},{"w":"around"},{"w":"data"},{"w":"entities"},{"w":"and"},{"w":"technical"},{"w":"layers"},{"w":"rather"},{"w":"than"},{"w":"around"},{"w":"the"},{"w":"processes"},{"w":"that"},{"w":"produce"},{"w":"value.","p":"sentence"},{"w":"Organisational"},{"w":"units"},{"w":"are"},{"w":"drawn"},{"w":"around"},{"w":"functions"},{"w":"like"},{"w":"digital,","p":"comma"},{"w":"operations,","p":"comma"},{"w":"risk,","p":"comma"},{"w":"and"},{"w":"compliance,","p":"comma"},{"w":"rather"},{"w":"than"},{"w":"around"},{"w":"the"},{"w":"processes"},{"w":"those"},{"w":"functions"},{"w":"serve.","p":"sentence"},{"w":"The"},{"w":"systems,","p":"comma"},{"w":"the"},{"w":"teams,","p":"comma"},{"w":"and"},{"w":"the"},{"w":"org"},{"w":"chart"},{"w":"all"},{"w":"describe"},{"w":"different"},{"w":"realities.","p":"sentence"},{"w":"No"},{"w":"one"},{"w":"can"},{"w":"reason"},{"w":"about"},{"w":"the"},{"w":"whole,","p":"comma"},{"w":"because"},{"w":"no"},{"w":"artefact"},{"w":"exists"},{"w":"that"},{"w":"holds"},{"w":"the"},{"w":"whole.","p":"paragraph"},{"w":"The"},{"w":"people"},{"w":"who"},{"w":"hold"},{"w":"the"},{"w":"whole"},{"w":"are"},{"w":"the"},{"w":"ones"},{"w":"who"},{"w":"have"},{"w":"been"},{"w":"there"},{"w":"longest.","p":"sentence"},{"w":"They"},{"w":"carry"},{"w":"the"},{"w":"real"},{"w":"processes"},{"w":"in"},{"w":"their"},{"w":"heads.","p":"sentence"},{"w":"Not"},{"w":"the"},{"w":"ones"},{"w":"in"},{"w":"the"},{"w":"compliance"},{"w":"register,","p":"comma"},{"w":"but"},{"w":"the"},{"w":"ones"},{"w":"that"},{"w":"actually"},{"w":"run"},{"w":"the"},{"w":"work.","p":"sentence"},{"w":"They"},{"w":"know"},{"w":"which"},{"w":"handoffs"},{"w":"fail,","p":"comma"},{"w":"which"},{"w":"exception"},{"w":"queues"},{"w":"grow,","p":"comma"},{"w":"and"},{"w":"which"},{"w":"workarounds"},{"w":"have"},{"w":"become"},{"w":"permanent.","p":"sentence"},{"w":"This"},{"w":"knowledge"},{"w":"is"},{"w":"the"},{"w":"organisation's"},{"w":"most"},{"w":"critical"},{"w":"asset.","p":"sentence"},{"w":"It"},{"w":"is"},{"w":"also"},{"w":"undocumented,","p":"comma"},{"w":"untransferable,","p":"comma"},{"w":"and"},{"w":"disappears"},{"w":"with"},{"w":"each"},{"w":"resignation.","p":"paragraph"},{"w":"In"},{"w":"organisations"},{"w":"where"},{"w":"engineers"},{"w":"work"},{"w":"in"},{"w":"the"},{"w":"business,","p":"comma"},{"w":"this"},{"w":"fragility"},{"w":"does"},{"w":"not"},{"w":"arise.","p":"sentence"},{"w":"Processes"},{"w":"are"},{"w":"the"},{"w":"substrate"},{"w":"of"},{"w":"execution,","p":"comma"},{"w":"and"},{"w":"customer"},{"w":"journeys"},{"w":"are"},{"w":"tests"},{"w":"of"},{"w":"whether"},{"w":"those"},{"w":"processes"},{"w":"deliver"},{"w":"value.","p":"sentence"},{"w":"When"},{"w":"the"},{"w":"two"},{"w":"are"},{"w":"explicit"},{"w":"and"},{"w":"unified,","p":"comma"},{"w":"the"},{"w":"organisation"},{"w":"can"},{"w":"reason"},{"w":"about"},{"w":"itself:","p":"comma"},{"w":"where"},{"w":"value"},{"w":"is"},{"w":"created,","p":"comma"},{"w":"where"},{"w":"it"},{"w":"is"},{"w":"destroyed,","p":"comma"},{"w":"and"},{"w":"who"},{"w":"is"},{"w":"responsible"},{"w":"for"},{"w":"each"},{"w":"transition.","p":"paragraph"},{"w":"The"},{"w":"antidote"},{"w":"is"},{"w":"not"},{"w":"to"},{"w":"choose"},{"w":"between"},{"w":"customer"},{"w":"journeys"},{"w":"and"},{"w":"business"},{"w":"processes.","p":"sentence"},{"w":"It"},{"w":"is"},{"w":"to"},{"w":"insist"},{"w":"they"},{"w":"are"},{"w":"the"},{"w":"same"},{"w":"thing,","p":"comma"},{"w":"expressed"},{"w":"at"},{"w":"different"},{"w":"levels"},{"w":"of"},{"w":"abstraction,","p":"comma"},{"w":"and"},{"w":"that"},{"w":"both"},{"w":"must"},{"w":"be"},{"w":"precise"},{"w":"enough"},{"w":"to"},{"w":"constrain"},{"w":"reality.","p":"sentence"},{"w":"This"},{"w":"raises"},{"w":"the"},{"w":"question"},{"w":"of"},{"w":"what"},{"w":"“precise"},{"w":"enough”"},{"w":"actually"},{"w":"means,","p":"comma"},{"w":"and"},{"w":"what"},{"w":"happens"},{"w":"when"},{"w":"an"},{"w":"organisation"},{"w":"writes"},{"w":"reality"},{"w":"down"},{"w":"properly"},{"w":"for"},{"w":"the"},{"w":"first"},{"w":"time.","p":"paragraph"},{"w":"An"},{"w":"organisation"},{"w":"fundamentally"},{"w":"cannot"},{"w":"own"},{"w":"core"},{"w":"processes"},{"w":"that"},{"w":"it"},{"w":"remains"},{"w":"unable"},{"w":"to"},{"w":"definitively"},{"w":"name.","p":"paragraph"}]