[{"w":"What"},{"w":"This"},{"w":"Looks"},{"w":"Like","p":"heading"},{"w":"The"},{"w":"first"},{"w":"thing"},{"w":"the"},{"w":"new"},{"w":"engineer"},{"w":"notices"},{"w":"is"},{"w":"the"},{"w":"silence.","p":"sentence"},{"w":"Not"},{"w":"literal"},{"w":"silence;","p":"comma"},{"w":"people"},{"w":"are"},{"w":"talking,","p":"comma"},{"w":"keyboards"},{"w":"are"},{"w":"clicking,","p":"comma"},{"w":"a"},{"w":"standup"},{"w":"is"},{"w":"wrapping"},{"w":"up"},{"w":"in"},{"w":"the"},{"w":"corner.","p":"sentence"},{"w":"The"},{"w":"silence"},{"w":"is"},{"w":"structural.","p":"sentence"},{"w":"No"},{"w":"one"},{"w":"is"},{"w":"on"},{"w":"a"},{"w":"bridge"},{"w":"call.","p":"sentence"},{"w":"No"},{"w":"one"},{"w":"is"},{"w":"in"},{"w":"a"},{"w":"dependency"},{"w":"meeting.","p":"sentence"},{"w":"No"},{"w":"one"},{"w":"is"},{"w":"waiting"},{"w":"for"},{"w":"an"},{"w":"approval"},{"w":"that"},{"w":"has"},{"w":"been"},{"w":"stuck"},{"w":"in"},{"w":"a"},{"w":"governance"},{"w":"queue"},{"w":"for"},{"w":"three"},{"w":"weeks.","p":"sentence"},{"w":"The"},{"w":"work"},{"w":"is"},{"w":"happening"},{"w":"where"},{"w":"the"},{"w":"work"},{"w":"lives,","p":"comma"},{"w":"owned"},{"w":"by"},{"w":"the"},{"w":"people"},{"w":"who"},{"w":"understand"},{"w":"it.","p":"paragraph"},{"w":"She"},{"w":"will"},{"w":"learn,","p":"comma"},{"w":"over"},{"w":"the"},{"w":"next"},{"w":"three"},{"w":"months,","p":"comma"},{"w":"that"},{"w":"this"},{"w":"is"},{"w":"what"},{"w":"clarity"},{"w":"sounds"},{"w":"like.","p":"separator"},{"w":"This"},{"w":"chapter"},{"w":"describes"},{"w":"a"},{"w":"year"},{"w":"in"},{"w":"the"},{"w":"life"},{"w":"of"},{"w":"an"},{"w":"organisation"},{"w":"that"},{"w":"has"},{"w":"made"},{"w":"the"},{"w":"transition.","p":"sentence"},{"w":"Not"},{"w":"a"},{"w":"utopia"},{"w":"but"},{"w":"a"},{"w":"realistic"},{"w":"picture,","p":"comma"},{"w":"with"},{"w":"remaining"},{"w":"tensions,","p":"comma"},{"w":"trade-"},{"w":"offs,","p":"comma"},{"w":"and"},{"w":"difficulties"},{"w":"acknowledged.","p":"sentence"},{"w":"The"},{"w":"problems"},{"w":"change"},{"w":"in"},{"w":"kind:","p":"comma"},{"w":"the"},{"w":"new"},{"w":"problems"},{"w":"are"},{"w":"the"},{"w":"kind"},{"w":"that"},{"w":"capable"},{"w":"people"},{"w":"can"},{"w":"solve.","p":"sentence"},{"w":"What"},{"w":"follows"},{"w":"is"},{"w":"drawn"},{"w":"from"},{"w":"real"},{"w":"transitions,","p":"comma"},{"w":"composited"},{"w":"and"},{"w":"fictionalised"},{"w":"as"},{"w":"elsewhere"},{"w":"in"},{"w":"the"},{"w":"book.","p":"sentence"},{"w":"Not"},{"w":"every"},{"w":"one"},{"w":"succeeded"},{"w":"fully.","p":"sentence"},{"w":"Some"},{"w":"stalled"},{"w":"when"},{"w":"political"},{"w":"will"},{"w":"ran"},{"w":"out.","p":"paragraph"},{"w":"The"},{"w":"Organisation","p":"heading"},{"w":"A"},{"w":"European"},{"w":"insurance"},{"w":"company"},{"w":"with"},{"w":"approximately"},{"w":"2,000"},{"w":"employees,","p":"comma"},{"w":"of"},{"w":"whom"},{"w":"around"},{"w":"400"},{"w":"work"},{"w":"in"},{"w":"technology.","p":"sentence"},{"w":"It"},{"w":"sells"},{"w":"motor,","p":"comma"},{"w":"home,","p":"comma"},{"w":"and"},{"w":"health"},{"w":"insurance"},{"w":"through"},{"w":"direct"},{"w":"and"},{"w":"broker"},{"w":"channels.","p":"sentence"},{"w":"Its"},{"w":"core"},{"w":"processes"},{"w":"are"},{"w":"mediated"},{"w":"entirely"},{"w":"through"},{"w":"software.","p":"sentence"},{"w":"It"},{"w":"is,","p":"comma"},{"w":"by"},{"w":"any"},{"w":"measure,","p":"comma"},{"w":"a"},{"w":"software-"},{"w":"dependent"},{"w":"corporate.","p":"paragraph"},{"w":"Eighteen"},{"w":"months"},{"w":"ago,","p":"comma"},{"w":"it"},{"w":"completed"},{"w":"a"},{"w":"restructuring.","p":"sentence"},{"w":"The"},{"w":"old"},{"w":"model,","p":"comma"},{"w":"a"},{"w":"technology"},{"w":"division"},{"w":"serving"},{"w":"“the"},{"w":"business”"},{"w":"through"},{"w":"project-"},{"w":"based"},{"w":"delivery"},{"w":"with"},{"w":"centralised"},{"w":"architecture"},{"w":"governance,","p":"comma"},{"w":"annual"},{"w":"budgets,","p":"comma"},{"w":"and"},{"w":"a"},{"w":"product"},{"w":"management"},{"w":"function"},{"w":"that"},{"w":"mediated"},{"w":"between"},{"w":"stakeholders"},{"w":"and"},{"w":"engineering,","p":"comma"},{"w":"was"},{"w":"replaced"},{"w":"with"},{"w":"autonomous"},{"w":"business"},{"w":"units"},{"w":"organised"},{"w":"around"},{"w":"core"},{"w":"processes.","p":"paragraph"},{"w":"The"},{"w":"transition"},{"w":"was"},{"w":"a"},{"w":"sequence"},{"w":"of"},{"w":"specific,","p":"comma"},{"w":"uncomfortable"},{"w":"decisions"},{"w":"rather"},{"w":"than"},{"w":"a"},{"w":"programme,","p":"comma"},{"w":"each"},{"w":"producing"},{"w":"a"},{"w":"reaction"},{"w":"the"},{"w":"next"},{"w":"decision"},{"w":"had"},{"w":"to"},{"w":"absorb.","p":"paragraph"},{"w":"The"},{"w":"programme"},{"w":"management"},{"w":"office"},{"w":"was"},{"w":"dissolved"},{"w":"in"},{"w":"the"},{"w":"third"},{"w":"month.","p":"sentence"},{"w":"The"},{"w":"programme"},{"w":"director,","p":"comma"},{"w":"a"},{"w":"woman"},{"w":"who"},{"w":"had"},{"w":"held"},{"w":"cross-"},{"w":"unit"},{"w":"dependencies"},{"w":"in"},{"w":"her"},{"w":"head"},{"w":"for"},{"w":"six"},{"w":"years,","p":"comma"},{"w":"was"},{"w":"told"},{"w":"her"},{"w":"function"},{"w":"was"},{"w":"being"},{"w":"eliminated,","p":"comma"},{"w":"not"},{"w":"repositioned.","p":"sentence"},{"w":"Her"},{"w":"objection"},{"w":"was"},{"w":"specific"},{"w":"and"},{"w":"legitimate:","p":"comma"},{"w":"who"},{"w":"would"},{"w":"track"},{"w":"the"},{"w":"cross-"},{"w":"unit"},{"w":"dependencies"},{"w":"that"},{"w":"her"},{"w":"office"},{"w":"currently"},{"w":"managed?","p":"sentence"},{"w":"Without"},{"w":"her"},{"w":"team,","p":"comma"},{"w":"she"},{"w":"said,","p":"comma"},{"w":"the"},{"w":"first"},{"w":"time"},{"w":"two"},{"w":"units"},{"w":"needed"},{"w":"to"},{"w":"coordinate"},{"w":"a"},{"w":"regulatory"},{"w":"change"},{"w":"across"},{"w":"a"},{"w":"shared"},{"w":"customer"},{"w":"journey,","p":"comma"},{"w":"nobody"},{"w":"would"},{"w":"know"},{"w":"who"},{"w":"owned"},{"w":"the"},{"w":"coordination.","p":"sentence"},{"w":"The"},{"w":"CEO's"},{"w":"response"},{"w":"was"},{"w":"equally"},{"w":"specific:","p":"comma"},{"w":"the"},{"w":"contracts"},{"w":"between"},{"w":"units"},{"w":"would"},{"w":"track"},{"w":"what"},{"w":"the"},{"w":"programme"},{"w":"office"},{"w":"tracked,","p":"comma"},{"w":"and"},{"w":"the"},{"w":"cross-"},{"w":"unit"},{"w":"synthesis"},{"w":"would"},{"w":"surface"},{"w":"the"},{"w":"dependencies"},{"w":"her"},{"w":"team"},{"w":"currently"},{"w":"surfaced"},{"w":"through"},{"w":"meetings.","p":"sentence"},{"w":"The"},{"w":"programme"},{"w":"director"},{"w":"understood"},{"w":"the"},{"w":"logic.","p":"sentence"},{"w":"She"},{"w":"also"},{"w":"understood"},{"w":"that"},{"w":"her"},{"w":"twelve"},{"w":"years"},{"w":"of"},{"w":"institutional"},{"w":"knowledge"},{"w":"about"},{"w":"which"},{"w":"dependencies"},{"w":"were"},{"w":"formal"},{"w":"and"},{"w":"which"},{"w":"were"},{"w":"informal,","p":"comma"},{"w":"which"},{"w":"escalation"},{"w":"paths"},{"w":"worked"},{"w":"and"},{"w":"which"},{"w":"were"},{"w":"performative,","p":"comma"},{"w":"would"},{"w":"not"},{"w":"transfer"},{"w":"to"},{"w":"a"},{"w":"contract"},{"w":"registry.","p":"sentence"},{"w":"She"},{"w":"was"},{"w":"right"},{"w":"about"},{"w":"that.","p":"sentence"},{"w":"The"},{"w":"organisation"},{"w":"absorbed"},{"w":"the"},{"w":"cost"},{"w":"over"},{"w":"the"},{"w":"following"},{"w":"two"},{"w":"quarters,","p":"comma"},{"w":"as"},{"w":"the"},{"w":"contract"},{"w":"boundaries"},{"w":"revealed"},{"w":"dependencies"},{"w":"her"},{"w":"team"},{"w":"had"},{"w":"been"},{"w":"managing"},{"w":"silently.","p":"paragraph"},{"w":"Two"},{"w":"layers"},{"w":"of"},{"w":"middle"},{"w":"management"},{"w":"were"},{"w":"removed.","p":"sentence"},{"w":"Three"},{"w":"senior"},{"w":"leaders"},{"w":"left.","p":"sentence"},{"w":"Forty"},{"w":"percent"},{"w":"of"},{"w":"the"},{"w":"product"},{"w":"management"},{"w":"function"},{"w":"was"},{"w":"eliminated"},{"w":"or"},{"w":"repositioned.","p":"paragraph"},{"w":"The"},{"w":"CFO's"},{"w":"resistance"},{"w":"arrived"},{"w":"not"},{"w":"as"},{"w":"opposition"},{"w":"but"},{"w":"as"},{"w":"a"},{"w":"procedural"},{"w":"objection.","p":"sentence"},{"w":"She"},{"w":"presented"},{"w":"the"},{"w":"existing"},{"w":"budget"},{"w":"model:","p":"comma"},{"w":"departmental"},{"w":"reporting,","p":"comma"},{"w":"quarterly"},{"w":"variance"},{"w":"analysis,","p":"comma"},{"w":"the"},{"w":"P&L"},{"w":"structure"},{"w":"the"},{"w":"board"},{"w":"had"},{"w":"reviewed"},{"w":"for"},{"w":"a"},{"w":"decade.","p":"sentence"},{"w":"The"},{"w":"CEO"},{"w":"presented"},{"w":"the"},{"w":"process-"},{"w":"level"},{"w":"model:","p":"comma"},{"w":"cost"},{"w":"traced"},{"w":"to"},{"w":"behaviour,","p":"comma"},{"w":"investment"},{"w":"connected"},{"w":"to"},{"w":"outcome,","p":"comma"},{"w":"each"},{"w":"unit's"},{"w":"operational"},{"w":"economics"},{"w":"visible"},{"w":"without"},{"w":"a"},{"w":"finance"},{"w":"team"},{"w":"constructing"},{"w":"the"},{"w":"answer"},{"w":"from"},{"w":"proxies.","p":"sentence"},{"w":"The"},{"w":"CFO's"},{"w":"objection"},{"w":"was"},{"w":"that"},{"w":"the"},{"w":"board"},{"w":"expected"},{"w":"departmental"},{"w":"reporting"},{"w":"and"},{"w":"would"},{"w":"not"},{"w":"accept"},{"w":"a"},{"w":"format"},{"w":"change"},{"w":"mid-"},{"w":"year.","p":"sentence"},{"w":"The"},{"w":"CEO"},{"w":"said"},{"w":"they"},{"w":"would"},{"w":"present"},{"w":"both"},{"w":"for"},{"w":"two"},{"w":"quarters,","p":"comma"},{"w":"until"},{"w":"the"},{"w":"board"},{"w":"saw"},{"w":"the"},{"w":"difference.","p":"sentence"},{"w":"The"},{"w":"CFO"},{"w":"agreed.","p":"sentence"},{"w":"Within"},{"w":"three"},{"w":"quarters,","p":"comma"},{"w":"the"},{"w":"board"},{"w":"stopped"},{"w":"asking"},{"w":"for"},{"w":"the"},{"w":"departmental"},{"w":"view.","p":"sentence"},{"w":"No"},{"w":"one"},{"w":"had"},{"w":"made"},{"w":"the"},{"w":"old"},{"w":"process"},{"w":"indefensible;","p":"comma"},{"w":"the"},{"w":"new"},{"w":"one"},{"w":"had"},{"w":"simply"},{"w":"made"},{"w":"it"},{"w":"redundant.","p":"paragraph"},{"w":"That"},{"w":"was"},{"w":"eighteen"},{"w":"months"},{"w":"ago.","p":"paragraph"},{"w":"The"},{"w":"organisation"},{"w":"now"},{"w":"operates"},{"w":"with"},{"w":"twelve"},{"w":"autonomous"},{"w":"business"},{"w":"units"},{"w":"and"},{"w":"three"},{"w":"platform"},{"w":"teams.","p":"paragraph"},{"w":"A"},{"w":"Monday"},{"w":"in"},{"w":"March","p":"heading"},{"w":"The"},{"w":"claims"},{"w":"management"},{"w":"unit"},{"w":"starts"},{"w":"the"},{"w":"week"},{"w":"with"},{"w":"a"},{"w":"fifteen-"},{"w":"minute"},{"w":"check-"},{"w":"in.","p":"sentence"},{"w":"The"},{"w":"team"},{"w":"reviews"},{"w":"the"},{"w":"weekly"},{"w":"synthesis"},{"w":"and"},{"w":"finds"},{"w":"a"},{"w":"drift"},{"w":"flag:","p":"comma"},{"w":"the"},{"w":"document"},{"w":"verification"},{"w":"step"},{"w":"includes"},{"w":"a"},{"w":"manual"},{"w":"compliance"},{"w":"check"},{"w":"that"},{"w":"the"},{"w":"process"},{"w":"definition"},{"w":"does"},{"w":"not"},{"w":"reflect.","p":"sentence"},{"w":"The"},{"w":"fix"},{"w":"is"},{"w":"straightforward"},{"w":"and"},{"w":"will"},{"w":"be"},{"w":"handled"},{"w":"before"},{"w":"lunch.","p":"paragraph"},{"w":"The"},{"w":"synthesis"},{"w":"also"},{"w":"flags"},{"w":"a"},{"w":"contract"},{"w":"violation"},{"w":"between"},{"w":"claims"},{"w":"and"},{"w":"payments:","p":"comma"},{"w":"a"},{"w":"field"},{"w":"populated"},{"w":"inconsistently.","p":"sentence"},{"w":"Tess,","p":"comma"},{"w":"the"},{"w":"claims"},{"w":"unit"},{"w":"lead,","p":"comma"},{"w":"recognises"},{"w":"it"},{"w":"as"},{"w":"a"},{"w":"planned"},{"w":"temporary"},{"w":"state"},{"w":"during"},{"w":"a"},{"w":"legacy"},{"w":"migration.","p":"sentence"},{"w":"She"},{"w":"annotates"},{"w":"the"},{"w":"exception"},{"w":"and"},{"w":"moves"},{"w":"on.","p":"paragraph"},{"w":"Meanwhile,","p":"comma"},{"w":"the"},{"w":"underwriting"},{"w":"unit"},{"w":"has"},{"w":"published"},{"w":"a"},{"w":"new"},{"w":"version"},{"w":"of"},{"w":"its"},{"w":"risk"},{"w":"assessment"},{"w":"contract:","p":"comma"},{"w":"a"},{"w":"boolean"},{"w":"flag"},{"w":"indicating"},{"w":"whether"},{"w":"the"},{"w":"applicant"},{"w":"has"},{"w":"an"},{"w":"existing"},{"w":"policy.","p":"sentence"},{"w":"The"},{"w":"claims"},{"w":"unit"},{"w":"consumes"},{"w":"this"},{"w":"event.","p":"sentence"},{"w":"The"},{"w":"AI"},{"w":"reader"},{"w":"detects"},{"w":"the"},{"w":"new"},{"w":"field"},{"w":"as"},{"w":"available"},{"w":"but"},{"w":"unconsumed.","p":"sentence"},{"w":"Tess"},{"w":"reads"},{"w":"the"},{"w":"notification"},{"w":"and"},{"w":"adds"},{"w":"it"},{"w":"to"},{"w":"the"},{"w":"improvement"},{"w":"backlog.","p":"sentence"},{"w":"No"},{"w":"coordination"},{"w":"meeting"},{"w":"is"},{"w":"held.","p":"sentence"},{"w":"The"},{"w":"contract"},{"w":"did"},{"w":"the"},{"w":"coordination.","p":"paragraph"},{"w":"Where"},{"w":"the"},{"w":"Model"},{"w":"Is"},{"w":"Hardest","p":"heading"},{"w":"Of"},{"w":"the"},{"w":"twelve"},{"w":"units,","p":"comma"},{"w":"eleven"},{"w":"have"},{"w":"reached"},{"w":"a"},{"w":"stable"},{"w":"operating"},{"w":"rhythm.","p":"sentence"},{"w":"The"},{"w":"twelfth,","p":"comma"},{"w":"broker"},{"w":"servicing,","p":"comma"},{"w":"has"},{"w":"not.","p":"paragraph"},{"w":"When"},{"w":"the"},{"w":"broker"},{"w":"servicing"},{"w":"unit"},{"w":"was"},{"w":"formed,","p":"comma"},{"w":"its"},{"w":"domain"},{"w":"expert"},{"w":"was"},{"w":"a"},{"w":"woman"},{"w":"named"},{"w":"Katja"},{"w":"who"},{"w":"had"},{"w":"spent"},{"w":"eight"},{"w":"years"},{"w":"navigating"},{"w":"the"},{"w":"regulatory"},{"w":"complexities"},{"w":"of"},{"w":"broker"},{"w":"agreements"},{"w":"across"},{"w":"three"},{"w":"jurisdictions.","p":"sentence"},{"w":"She"},{"w":"understood"},{"w":"which"},{"w":"commission"},{"w":"structures"},{"w":"were"},{"w":"grandfathered"},{"w":"under"},{"w":"previous"},{"w":"regulations,","p":"comma"},{"w":"which"},{"w":"onboarding"},{"w":"requirements"},{"w":"were"},{"w":"statutory"},{"w":"and"},{"w":"which"},{"w":"were"},{"w":"conventional,","p":"comma"},{"w":"and"},{"w":"where"},{"w":"the"},{"w":"real"},{"w":"compliance"},{"w":"risks"},{"w":"lived.","p":"sentence"},{"w":"This"},{"w":"knowledge"},{"w":"existed"},{"w":"nowhere"},{"w":"in"},{"w":"the"},{"w":"organisation's"},{"w":"documentation"},{"w":"because"},{"w":"the"},{"w":"documentation"},{"w":"had"},{"w":"never"},{"w":"been"},{"w":"written"},{"w":"to"},{"w":"that"},{"w":"level"},{"w":"of"},{"w":"specificity.","p":"paragraph"},{"w":"The"},{"w":"process"},{"w":"definition"},{"w":"the"},{"w":"unit"},{"w":"produced"},{"w":"was"},{"w":"precise"},{"w":"and"},{"w":"versioned.","p":"sentence"},{"w":"It"},{"w":"captured"},{"w":"the"},{"w":"states,","p":"comma"},{"w":"transitions,","p":"comma"},{"w":"and"},{"w":"failure"},{"w":"modes"},{"w":"that"},{"w":"the"},{"w":"team"},{"w":"could"},{"w":"articulate.","p":"sentence"},{"w":"It"},{"w":"captured"},{"w":"perhaps"},{"w":"half"},{"w":"of"},{"w":"what"},{"w":"Katja"},{"w":"knew.","p":"sentence"},{"w":"The"},{"w":"other"},{"w":"half"},{"w":"was"},{"w":"regulatory"},{"w":"nuance"},{"w":"accumulated"},{"w":"over"},{"w":"eight"},{"w":"years:","p":"comma"},{"w":"which"},{"w":"provisions"},{"w":"were"},{"w":"negotiable,","p":"comma"},{"w":"which"},{"w":"edge"},{"w":"cases"},{"w":"the"},{"w":"system"},{"w":"handled"},{"w":"through"},{"w":"manual"},{"w":"workarounds,","p":"comma"},{"w":"which"},{"w":"broker"},{"w":"relationships"},{"w":"predated"},{"w":"the"},{"w":"current"},{"w":"framework.","p":"sentence"},{"w":"These"},{"w":"details"},{"w":"lived"},{"w":"in"},{"w":"Katja's"},{"w":"head,","p":"comma"},{"w":"not"},{"w":"because"},{"w":"she"},{"w":"was"},{"w":"hoarding"},{"w":"them,","p":"comma"},{"w":"but"},{"w":"because"},{"w":"no"},{"w":"artefact"},{"w":"in"},{"w":"the"},{"w":"organisation"},{"w":"had"},{"w":"ever"},{"w":"been"},{"w":"designed"},{"w":"to"},{"w":"receive"},{"w":"them.","p":"paragraph"},{"w":"Six"},{"w":"months"},{"w":"into"},{"w":"the"},{"w":"transition,","p":"comma"},{"w":"Katja"},{"w":"accepted"},{"w":"an"},{"w":"offer"},{"w":"from"},{"w":"a"},{"w":"competitor.","p":"sentence"},{"w":"The"},{"w":"reasons"},{"w":"were"},{"w":"personal:","p":"comma"},{"w":"a"},{"w":"shorter"},{"w":"commute,","p":"comma"},{"w":"a"},{"w":"role"},{"w":"closer"},{"w":"to"},{"w":"her"},{"w":"children's"},{"w":"school.","p":"sentence"},{"w":"She"},{"w":"gave"},{"w":"four"},{"w":"weeks'"},{"w":"notice.","p":"sentence"},{"w":"The"},{"w":"unit"},{"w":"lead,","p":"comma"},{"w":"a"},{"w":"senior"},{"w":"architect"},{"w":"named"},{"w":"Henrik,","p":"comma"},{"w":"spent"},{"w":"those"},{"w":"four"},{"w":"weeks"},{"w":"trying"},{"w":"to"},{"w":"extract"},{"w":"what"},{"w":"Katja"},{"w":"carried.","p":"sentence"},{"w":"They"},{"w":"produced"},{"w":"forty"},{"w":"pages"},{"w":"of"},{"w":"notes,","p":"comma"},{"w":"detailed"},{"w":"and"},{"w":"precise,","p":"comma"},{"w":"covering"},{"w":"perhaps"},{"w":"half"},{"w":"of"},{"w":"what"},{"w":"she"},{"w":"knew.","p":"paragraph"},{"w":"Her"},{"w":"replacement,","p":"comma"},{"w":"David,","p":"comma"},{"w":"arrived"},{"w":"from"},{"w":"a"},{"w":"different"},{"w":"part"},{"w":"of"},{"w":"the"},{"w":"insurance"},{"w":"industry.","p":"sentence"},{"w":"He"},{"w":"was"},{"w":"competent"},{"w":"and"},{"w":"motivated.","p":"sentence"},{"w":"He"},{"w":"did"},{"w":"not"},{"w":"know"},{"w":"that"},{"w":"broker"},{"w":"commission"},{"w":"reconciliation"},{"w":"in"},{"w":"the"},{"w":"group"},{"w":"scheme"},{"w":"channel"},{"w":"operated"},{"w":"under"},{"w":"different"},{"w":"rounding"},{"w":"rules"},{"w":"than"},{"w":"individual"},{"w":"policies,","p":"comma"},{"w":"a"},{"w":"distinction"},{"w":"handled"},{"w":"through"},{"w":"a"},{"w":"manual"},{"w":"adjustment"},{"w":"that"},{"w":"Katja"},{"w":"performed"},{"w":"quarterly.","p":"sentence"},{"w":"He"},{"w":"did"},{"w":"not"},{"w":"know"},{"w":"that"},{"w":"three"},{"w":"of"},{"w":"the"},{"w":"organisation's"},{"w":"largest"},{"w":"broker"},{"w":"relationships"},{"w":"had"},{"w":"onboarding"},{"w":"agreements"},{"w":"that"},{"w":"predated"},{"w":"the"},{"w":"current"},{"w":"regulatory"},{"w":"framework.","p":"paragraph"},{"w":"By"},{"w":"month"},{"w":"nine,","p":"comma"},{"w":"the"},{"w":"contracts"},{"w":"governing"},{"w":"interactions"},{"w":"between"},{"w":"broker"},{"w":"servicing"},{"w":"and"},{"w":"its"},{"w":"three"},{"w":"adjacent"},{"w":"units"},{"w":"were"},{"w":"being"},{"w":"renegotiated"},{"w":"for"},{"w":"the"},{"w":"second"},{"w":"time.","p":"sentence"},{"w":"Without"},{"w":"Katja's"},{"w":"regulatory"},{"w":"context,","p":"comma"},{"w":"the"},{"w":"boundaries"},{"w":"felt"},{"w":"arbitrary"},{"w":"to"},{"w":"the"},{"w":"people"},{"w":"who"},{"w":"had"},{"w":"to"},{"w":"maintain"},{"w":"them.","p":"sentence"},{"w":"Henrik"},{"w":"found"},{"w":"himself"},{"w":"in"},{"w":"weekly"},{"w":"negotiations"},{"w":"with"},{"w":"the"},{"w":"origination"},{"w":"unit"},{"w":"leads,","p":"comma"},{"w":"defending"},{"w":"boundary"},{"w":"decisions"},{"w":"whose"},{"w":"rationale"},{"w":"he"},{"w":"could"},{"w":"articulate"},{"w":"from"},{"w":"the"},{"w":"notes"},{"w":"but"},{"w":"could"},{"w":"not"},{"w":"fully"},{"w":"justify"},{"w":"from"},{"w":"experience.","p":"paragraph"},{"w":"The"},{"w":"unit's"},{"w":"metrics"},{"w":"reflected"},{"w":"the"},{"w":"strain.","p":"sentence"},{"w":"Broker"},{"w":"onboarding"},{"w":"time,","p":"comma"},{"w":"which"},{"w":"had"},{"w":"improved"},{"w":"by"},{"w":"twenty"},{"w":"percent"},{"w":"in"},{"w":"the"},{"w":"first"},{"w":"five"},{"w":"months,","p":"comma"},{"w":"regressed"},{"w":"to"},{"w":"within"},{"w":"five"},{"w":"percent"},{"w":"of"},{"w":"the"},{"w":"pre-"},{"w":"transition"},{"w":"baseline.","p":"sentence"},{"w":"Commission"},{"w":"reconciliation"},{"w":"errors"},{"w":"plateaued.","p":"sentence"},{"w":"The"},{"w":"weekly"},{"w":"synthesis"},{"w":"flagged"},{"w":"the"},{"w":"same"},{"w":"drift"},{"w":"repeatedly:","p":"comma"},{"w":"the"},{"w":"process"},{"w":"definition"},{"w":"described"},{"w":"states"},{"w":"and"},{"w":"transitions"},{"w":"that"},{"w":"the"},{"w":"system"},{"w":"still"},{"w":"implemented"},{"w":"correctly,","p":"comma"},{"w":"but"},{"w":"the"},{"w":"exception"},{"w":"handling"},{"w":"that"},{"w":"Katja"},{"w":"had"},{"w":"managed"},{"w":"informally"},{"w":"was"},{"w":"generating"},{"w":"a"},{"w":"steady"},{"w":"stream"},{"w":"of"},{"w":"manual"},{"w":"interventions"},{"w":"that"},{"w":"nobody"},{"w":"had"},{"w":"written"},{"w":"into"},{"w":"the"},{"w":"definition.","p":"paragraph"},{"w":"Henrik"},{"w":"sat"},{"w":"in"},{"w":"the"},{"w":"Monday"},{"w":"check-"},{"w":"in"},{"w":"and"},{"w":"read"},{"w":"the"},{"w":"synthesis"},{"w":"output.","p":"sentence"},{"w":"The"},{"w":"AI"},{"w":"reader"},{"w":"had"},{"w":"correctly"},{"w":"identified"},{"w":"that"},{"w":"the"},{"w":"unit's"},{"w":"process"},{"w":"definition"},{"w":"did"},{"w":"not"},{"w":"account"},{"w":"for"},{"w":"the"},{"w":"grandfathered"},{"w":"commission"},{"w":"structures.","p":"sentence"},{"w":"It"},{"w":"recommended"},{"w":"updating"},{"w":"the"},{"w":"definition.","p":"sentence"},{"w":"The"},{"w":"recommendation"},{"w":"was"},{"w":"accurate"},{"w":"and"},{"w":"insufficient.","p":"sentence"},{"w":"The"},{"w":"problem"},{"w":"was"},{"w":"that"},{"w":"Henrik"},{"w":"did"},{"w":"not"},{"w":"yet"},{"w":"have"},{"w":"anyone"},{"w":"who"},{"w":"understood"},{"w":"the"},{"w":"domain"},{"w":"well"},{"w":"enough"},{"w":"to"},{"w":"update"},{"w":"it"},{"w":"correctly.","p":"sentence"},{"w":"David"},{"w":"was"},{"w":"learning,","p":"comma"},{"w":"but"},{"w":"learning"},{"w":"takes"},{"w":"time.","p":"paragraph"},{"w":"The"},{"w":"honest"},{"w":"assessment"},{"w":"at"},{"w":"twelve"},{"w":"months:","p":"comma"},{"w":"broker"},{"w":"servicing"},{"w":"was"},{"w":"worse"},{"w":"than"},{"w":"Henrik"},{"w":"had"},{"w":"expected"},{"w":"and"},{"w":"still"},{"w":"better"},{"w":"than"},{"w":"what"},{"w":"it"},{"w":"had"},{"w":"replaced.","p":"sentence"},{"w":"Under"},{"w":"the"},{"w":"old"},{"w":"structure,","p":"comma"},{"w":"the"},{"w":"same"},{"w":"commission"},{"w":"reconciliation"},{"w":"errors"},{"w":"had"},{"w":"occurred,","p":"comma"},{"w":"but"},{"w":"they"},{"w":"had"},{"w":"been"},{"w":"invisible,","p":"comma"},{"w":"absorbed"},{"w":"by"},{"w":"Katja's"},{"w":"quarterly"},{"w":"manual"},{"w":"adjustments"},{"w":"and"},{"w":"never"},{"w":"surfaced"},{"w":"in"},{"w":"any"},{"w":"report.","p":"sentence"},{"w":"The"},{"w":"onboarding"},{"w":"delays"},{"w":"had"},{"w":"existed"},{"w":"before,","p":"comma"},{"w":"distributed"},{"w":"across"},{"w":"three"},{"w":"departments"},{"w":"and"},{"w":"attributed"},{"w":"to"},{"w":"“process"},{"w":"complexity.”"},{"w":"The"},{"w":"unit"},{"w":"had"},{"w":"made"},{"w":"the"},{"w":"dysfunction"},{"w":"visible"},{"w":"without"},{"w":"yet"},{"w":"having"},{"w":"the"},{"w":"depth"},{"w":"to"},{"w":"resolve"},{"w":"it.","p":"paragraph"},{"w":"Henrik"},{"w":"did"},{"w":"not"},{"w":"describe"},{"w":"this"},{"w":"as"},{"w":"a"},{"w":"success.","p":"sentence"},{"w":"He"},{"w":"described"},{"w":"it"},{"w":"as"},{"w":"a"},{"w":"unit"},{"w":"that"},{"w":"had"},{"w":"exposed"},{"w":"problems"},{"w":"the"},{"w":"organisation"},{"w":"had"},{"w":"previously"},{"w":"chosen"},{"w":"not"},{"w":"to"},{"w":"see,","p":"comma"},{"w":"and"},{"w":"that"},{"w":"did"},{"w":"not"},{"w":"yet"},{"w":"have"},{"w":"the"},{"w":"capability"},{"w":"to"},{"w":"fix"},{"w":"all"},{"w":"of"},{"w":"them.","p":"sentence"},{"w":"Under"},{"w":"the"},{"w":"old"},{"w":"structure,","p":"comma"},{"w":"the"},{"w":"problems"},{"w":"would"},{"w":"have"},{"w":"remained"},{"w":"invisible"},{"w":"until"},{"w":"Katja"},{"w":"left"},{"w":"and"},{"w":"nobody"},{"w":"knew"},{"w":"how"},{"w":"to"},{"w":"perform"},{"w":"the"},{"w":"quarterly"},{"w":"adjustment.","p":"sentence"},{"w":"Under"},{"w":"the"},{"w":"new"},{"w":"structure,","p":"comma"},{"w":"the"},{"w":"problems"},{"w":"were"},{"w":"named,","p":"comma"},{"w":"tracked,","p":"comma"},{"w":"and"},{"w":"slowly"},{"w":"being"},{"w":"addressed.","p":"sentence"},{"w":"This"},{"w":"is"},{"w":"what"},{"w":"the"},{"w":"model"},{"w":"looks"},{"w":"like"},{"w":"when"},{"w":"it"},{"w":"is"},{"w":"hard.","p":"sentence"},{"w":"The"},{"w":"dysfunction"},{"w":"is"},{"w":"visible.","p":"sentence"},{"w":"The"},{"w":"ownership"},{"w":"is"},{"w":"clear.","p":"sentence"},{"w":"The"},{"w":"improvement"},{"w":"is"},{"w":"slow"},{"w":"and"},{"w":"real.","p":"paragraph"},{"w":"Broker"},{"w":"servicing"},{"w":"is"},{"w":"the"},{"w":"weakest"},{"w":"unit.","p":"sentence"},{"w":"It"},{"w":"is"},{"w":"also"},{"w":"the"},{"w":"most"},{"w":"honest"},{"w":"test"},{"w":"of"},{"w":"the"},{"w":"model,","p":"comma"},{"w":"because"},{"w":"it"},{"w":"shows"},{"w":"what"},{"w":"happens"},{"w":"when"},{"w":"the"},{"w":"transition"},{"w":"is"},{"w":"hard"},{"w":"and"},{"w":"the"},{"w":"people"},{"w":"inside"},{"w":"it"},{"w":"are"},{"w":"uncertain.","p":"sentence"},{"w":"The"},{"w":"model"},{"w":"did"},{"w":"not"},{"w":"prevent"},{"w":"the"},{"w":"loss"},{"w":"of"},{"w":"Katja's"},{"w":"knowledge.","p":"sentence"},{"w":"What"},{"w":"it"},{"w":"did"},{"w":"was"},{"w":"make"},{"w":"the"},{"w":"consequences"},{"w":"visible,","p":"comma"},{"w":"attributable,","p":"comma"},{"w":"and"},{"w":"addressable.","p":"paragraph"},{"w":"The"},{"w":"Costs"},{"w":"That"},{"w":"Were"},{"w":"Always"},{"w":"There","p":"heading"},{"w":"The"},{"w":"claims"},{"w":"unit's"},{"w":"performance"},{"w":"in"},{"w":"Q1"},{"w":"makes"},{"w":"it"},{"w":"the"},{"w":"most"},{"w":"visible"},{"w":"evidence"},{"w":"of"},{"w":"the"},{"w":"model's"},{"w":"success,","p":"comma"},{"w":"which"},{"w":"is"},{"w":"also"},{"w":"why"},{"w":"it"},{"w":"is"},{"w":"the"},{"w":"most"},{"w":"politically"},{"w":"exposed.","p":"sentence"},{"w":"By"},{"w":"March,","p":"comma"},{"w":"two"},{"w":"department"},{"w":"heads"},{"w":"whose"},{"w":"functions"},{"w":"were"},{"w":"eliminated"},{"w":"in"},{"w":"the"},{"w":"restructuring"},{"w":"have"},{"w":"begun"},{"w":"describing"},{"w":"the"},{"w":"claims"},{"w":"unit's"},{"w":"improvements"},{"w":"as"},{"w":"“unsustainable”"},{"w":"in"},{"w":"conversations"},{"w":"with"},{"w":"the"},{"w":"CFO.","p":"sentence"},{"w":"One"},{"w":"has"},{"w":"commissioned"},{"w":"an"},{"w":"analysis"},{"w":"suggesting"},{"w":"the"},{"w":"unit's"},{"w":"resolution"},{"w":"time"},{"w":"improvements"},{"w":"are"},{"w":"partly"},{"w":"attributable"},{"w":"to"},{"w":"seasonal"},{"w":"claim"},{"w":"patterns"},{"w":"rather"},{"w":"than"},{"w":"structural"},{"w":"change.","p":"sentence"},{"w":"The"},{"w":"analysis"},{"w":"is"},{"w":"not"},{"w":"wrong"},{"w":"in"},{"w":"its"},{"w":"components"},{"w":"and"},{"w":"is"},{"w":"misleading"},{"w":"in"},{"w":"its"},{"w":"framing.","p":"sentence"},{"w":"Tess"},{"w":"receives"},{"w":"a"},{"w":"copy"},{"w":"from"},{"w":"a"},{"w":"colleague"},{"w":"and"},{"w":"spends"},{"w":"forty"},{"w":"minutes"},{"w":"constructing"},{"w":"the"},{"w":"counter-"},{"w":"evidence"},{"w":"before"},{"w":"deciding"},{"w":"the"},{"w":"better"},{"w":"use"},{"w":"of"},{"w":"her"},{"w":"time"},{"w":"is"},{"w":"updating"},{"w":"the"},{"w":"process"},{"w":"definition"},{"w":"with"},{"w":"the"},{"w":"Q1"},{"w":"metric"},{"w":"reconciliation.","p":"paragraph"},{"w":"She"},{"w":"is"},{"w":"right.","p":"sentence"},{"w":"The"},{"w":"counter-"},{"w":"evidence"},{"w":"exists"},{"w":"in"},{"w":"the"},{"w":"synthesis,","p":"comma"},{"w":"and"},{"w":"the"},{"w":"CEO"},{"w":"has"},{"w":"read"},{"w":"it.","p":"sentence"},{"w":"But"},{"w":"the"},{"w":"pattern"},{"w":"is"},{"w":"worth"},{"w":"naming:","p":"comma"},{"w":"a"},{"w":"model"},{"w":"that"},{"w":"makes"},{"w":"performance"},{"w":"visible"},{"w":"also"},{"w":"makes"},{"w":"the"},{"w":"comparison"},{"w":"with"},{"w":"non-"},{"w":"performing"},{"w":"structures"},{"w":"visible,","p":"comma"},{"w":"and"},{"w":"the"},{"w":"non-"},{"w":"performing"},{"w":"structures"},{"w":"will"},{"w":"contest"},{"w":"the"},{"w":"measurement"},{"w":"before"},{"w":"they"},{"w":"accept"},{"w":"the"},{"w":"verdict.","p":"paragraph"},{"w":"The"},{"w":"infrastructure"},{"w":"platform"},{"w":"team"},{"w":"has"},{"w":"been"},{"w":"the"},{"w":"model's"},{"w":"quiet"},{"w":"success"},{"w":"and"},{"w":"its"},{"w":"quietly"},{"w":"developing"},{"w":"problem.","p":"sentence"},{"w":"In"},{"w":"the"},{"w":"first"},{"w":"year,","p":"comma"},{"w":"it"},{"w":"provided"},{"w":"deployment"},{"w":"capability"},{"w":"and"},{"w":"observability"},{"w":"tooling"},{"w":"without"},{"w":"accumulating"},{"w":"governance"},{"w":"function.","p":"sentence"},{"w":"By"},{"w":"Q2"},{"w":"of"},{"w":"the"},{"w":"second"},{"w":"year,","p":"comma"},{"w":"it"},{"w":"has"},{"w":"begun"},{"w":"requesting"},{"w":"advance"},{"w":"notice"},{"w":"of"},{"w":"contract"},{"w":"changes"},{"w":"that"},{"w":"involve"},{"w":"API"},{"w":"schema"},{"w":"modifications.","p":"sentence"},{"w":"The"},{"w":"request"},{"w":"is"},{"w":"reasonable"},{"w":"on"},{"w":"its"},{"w":"face"},{"w":"(schema"},{"w":"changes"},{"w":"can"},{"w":"affect"},{"w":"shared"},{"w":"tooling)"},{"w":"and"},{"w":"it"},{"w":"is"},{"w":"the"},{"w":"beginning"},{"w":"of"},{"w":"something"},{"w":"the"},{"w":"book"},{"w":"has"},{"w":"already"},{"w":"named.","p":"sentence"},{"w":"The"},{"w":"CEO"},{"w":"sees"},{"w":"it"},{"w":"in"},{"w":"the"},{"w":"cross-"},{"w":"unit"},{"w":"synthesis"},{"w":"as"},{"w":"a"},{"w":"new"},{"w":"coordination"},{"w":"step"},{"w":"appearing"},{"w":"in"},{"w":"three"},{"w":"units'"},{"w":"process"},{"w":"definitions.","p":"sentence"},{"w":"She"},{"w":"raises"},{"w":"it"},{"w":"with"},{"w":"the"},{"w":"CTO"},{"w":"in"},{"w":"their"},{"w":"next"},{"w":"one-"},{"w":"to-"},{"w":"one.","p":"sentence"},{"w":"He"},{"w":"schedules"},{"w":"a"},{"w":"conversation"},{"w":"with"},{"w":"the"},{"w":"platform"},{"w":"lead.","p":"sentence"},{"w":"The"},{"w":"conversation"},{"w":"surfaces"},{"w":"the"},{"w":"platform"},{"w":"team's"},{"w":"legitimate"},{"w":"concern"},{"w":"and"},{"w":"the"},{"w":"structural"},{"w":"drift"},{"w":"it"},{"w":"represents.","p":"sentence"},{"w":"They"},{"w":"resolve"},{"w":"it"},{"w":"by"},{"w":"publishing"},{"w":"a"},{"w":"clear"},{"w":"boundary:","p":"comma"},{"w":"the"},{"w":"platform"},{"w":"team"},{"w":"is"},{"w":"notified"},{"w":"of"},{"w":"schema"},{"w":"changes,","p":"comma"},{"w":"not"},{"w":"consulted"},{"w":"on"},{"w":"them.","p":"sentence"},{"w":"The"},{"w":"notification"},{"w":"happens"},{"w":"automatically"},{"w":"through"},{"w":"the"},{"w":"contract"},{"w":"registry.","p":"sentence"},{"w":"No"},{"w":"approval"},{"w":"process"},{"w":"is"},{"w":"created.","p":"sentence"},{"w":"The"},{"w":"drift"},{"w":"is"},{"w":"contained"},{"w":"before"},{"w":"it"},{"w":"becomes"},{"w":"a"},{"w":"pattern.","p":"paragraph"},{"w":"These"},{"w":"are"},{"w":"the"},{"w":"maintenance"},{"w":"costs"},{"w":"of"},{"w":"a"},{"w":"working"},{"w":"structure.","p":"sentence"},{"w":"They"},{"w":"are"},{"w":"qualitatively"},{"w":"different"},{"w":"from"},{"w":"the"},{"w":"structural"},{"w":"failures"},{"w":"the"},{"w":"model"},{"w":"replaced:","p":"comma"},{"w":"not"},{"w":"invisible"},{"w":"accumulations"},{"w":"of"},{"w":"dysfunction,","p":"comma"},{"w":"but"},{"w":"named,","p":"comma"},{"w":"attributable,","p":"comma"},{"w":"resolvable"},{"w":"problems.","p":"sentence"},{"w":"The"},{"w":"distinction"},{"w":"is"},{"w":"not"},{"w":"comfort"},{"w":"but"},{"w":"the"},{"w":"difference"},{"w":"between"},{"w":"problems"},{"w":"that"},{"w":"respond"},{"w":"to"},{"w":"owners"},{"w":"and"},{"w":"problems"},{"w":"that"},{"w":"require"},{"w":"committees.","p":"paragraph"},{"w":"How"},{"w":"the"},{"w":"System"},{"w":"Responds","p":"heading"},{"w":"The"},{"w":"contrast"},{"w":"with"},{"w":"broker"},{"w":"servicing"},{"w":"makes"},{"w":"the"},{"w":"other"},{"w":"units'"},{"w":"performance"},{"w":"legible.","p":"sentence"},{"w":"A"},{"w":"Thursday"},{"w":"afternoon"},{"w":"illustrates"},{"w":"the"},{"w":"difference.","p":"paragraph"},{"w":"The"},{"w":"payments"},{"w":"platform"},{"w":"experiences"},{"w":"a"},{"w":"latency"},{"w":"spike"},{"w":"that"},{"w":"causes"},{"w":"some"},{"w":"premium"},{"w":"collection"},{"w":"transactions"},{"w":"to"},{"w":"time"},{"w":"out.","p":"sentence"},{"w":"The"},{"w":"payments"},{"w":"unit"},{"w":"detects"},{"w":"it"},{"w":"within"},{"w":"ninety"},{"w":"seconds.","p":"sentence"},{"w":"The"},{"w":"responsible"},{"w":"engineer"},{"w":"identifies"},{"w":"the"},{"w":"cause"},{"w":"within"},{"w":"twenty"},{"w":"minutes:","p":"comma"},{"w":"a"},{"w":"database"},{"w":"query"},{"w":"scanning"},{"w":"a"},{"w":"larger-"},{"w":"than-"},{"w":"expected"},{"w":"index.","p":"sentence"},{"w":"She"},{"w":"deploys"},{"w":"a"},{"w":"fix.","p":"sentence"},{"w":"Total"},{"w":"resolution:","p":"comma"},{"w":"thirty-"},{"w":"four"},{"w":"minutes"},{"w":"from"},{"w":"detection.","p":"paragraph"},{"w":"Tess"},{"w":"notices"},{"w":"it"},{"w":"from"},{"w":"the"},{"w":"claims"},{"w":"side"},{"w":"when"},{"w":"two"},{"w":"settlement"},{"w":"confirmations"},{"w":"stall;","p":"comma"},{"w":"the"},{"w":"resolution"},{"w":"arrives"},{"w":"before"},{"w":"she"},{"w":"has"},{"w":"finished"},{"w":"drafting"},{"w":"the"},{"w":"message.","p":"sentence"},{"w":"In"},{"w":"the"},{"w":"old"},{"w":"structure,","p":"comma"},{"w":"the"},{"w":"same"},{"w":"spike"},{"w":"would"},{"w":"have"},{"w":"triggered"},{"w":"a"},{"w":"bridge"},{"w":"call"},{"w":"with"},{"w":"twenty"},{"w":"participants,","p":"comma"},{"w":"and"},{"w":"the"},{"w":"payments"},{"w":"unit"},{"w":"lead"},{"w":"would"},{"w":"have"},{"w":"spent"},{"w":"forty"},{"w":"minutes"},{"w":"establishing"},{"w":"process"},{"w":"ownership"},{"w":"before"},{"w":"anyone"},{"w":"diagnosed"},{"w":"the"},{"w":"cause.","p":"paragraph"},{"w":"At"},{"w":"the"},{"w":"end"},{"w":"of"},{"w":"Q1,","p":"comma"},{"w":"the"},{"w":"CEO"},{"w":"reviews"},{"w":"the"},{"w":"quarter"},{"w":"using"},{"w":"the"},{"w":"AI-"},{"w":"generated"},{"w":"synthesis.","p":"sentence"},{"w":"Four"},{"w":"of"},{"w":"six"},{"w":"strategic"},{"w":"commitments"},{"w":"are"},{"w":"on"},{"w":"track.","p":"sentence"},{"w":"One"},{"w":"(claims"},{"w":"leakage)"},{"w":"is"},{"w":"behind;","p":"comma"},{"w":"Tess"},{"w":"confirms"},{"w":"the"},{"w":"triage"},{"w":"change"},{"w":"is"},{"w":"scoped.","p":"sentence"},{"w":"One"},{"w":"(broker"},{"w":"onboarding"},{"w":"time)"},{"w":"has"},{"w":"not"},{"w":"been"},{"w":"addressed,","p":"comma"},{"w":"for"},{"w":"the"},{"w":"reasons"},{"w":"Henrik"},{"w":"has"},{"w":"been"},{"w":"transparent"},{"w":"about.","p":"sentence"},{"w":"The"},{"w":"CEO"},{"w":"pushes"},{"w":"back"},{"w":"on"},{"w":"the"},{"w":"broker"},{"w":"servicing"},{"w":"unit"},{"w":"lead,","p":"comma"},{"w":"who"},{"w":"explains"},{"w":"the"},{"w":"regulatory"},{"w":"scope"},{"w":"that"},{"w":"consumed"},{"w":"his"},{"w":"best"},{"w":"engineer"},{"w":"for"},{"w":"six"},{"w":"weeks.","p":"sentence"},{"w":"The"},{"w":"disagreement"},{"w":"is"},{"w":"not"},{"w":"resolved.","p":"sentence"},{"w":"The"},{"w":"commitment"},{"w":"moves"},{"w":"to"},{"w":"Q2.","p":"paragraph"},{"w":"Total"},{"w":"incident"},{"w":"count:","p":"comma"},{"w":"twenty-"},{"w":"three,","p":"comma"},{"w":"down"},{"w":"from"},{"w":"forty-"},{"w":"one"},{"w":"in"},{"w":"the"},{"w":"previous"},{"w":"quarter.","p":"sentence"},{"w":"Average"},{"w":"resolution"},{"w":"time:","p":"comma"},{"w":"fifty-"},{"w":"one"},{"w":"minutes,","p":"comma"},{"w":"down"},{"w":"from"},{"w":"three"},{"w":"hours"},{"w":"and"},{"w":"twelve"},{"w":"minutes.","p":"sentence"},{"w":"The"},{"w":"review"},{"w":"meeting"},{"w":"lasts"},{"w":"ninety"},{"w":"minutes,","p":"comma"},{"w":"grounded"},{"w":"in"},{"w":"evidence"},{"w":"rather"},{"w":"than"},{"w":"narrative.","p":"paragraph"},{"w":"What"},{"w":"Remains"},{"w":"Difficult","p":"heading"},{"w":"Contract"},{"w":"negotiations"},{"w":"are"},{"w":"sometimes"},{"w":"contentious.","p":"sentence"},{"w":"When"},{"w":"two"},{"w":"units"},{"w":"need"},{"w":"to"},{"w":"change"},{"w":"a"},{"w":"shared"},{"w":"contract,","p":"comma"},{"w":"the"},{"w":"negotiation"},{"w":"requires"},{"w":"agreement.","p":"sentence"},{"w":"There"},{"w":"is"},{"w":"no"},{"w":"authority"},{"w":"to"},{"w":"appeal"},{"w":"to.","p":"sentence"},{"w":"This"},{"w":"is"},{"w":"harder"},{"w":"in"},{"w":"some"},{"w":"ways,","p":"comma"},{"w":"better"},{"w":"in"},{"w":"others.","p":"paragraph"},{"w":"Platform"},{"w":"teams"},{"w":"require"},{"w":"constant"},{"w":"vigilance.","p":"sentence"},{"w":"The"},{"w":"infrastructure"},{"w":"team"},{"w":"has"},{"w":"periodically"},{"w":"attempted"},{"w":"to"},{"w":"require"},{"w":"approval"},{"w":"for"},{"w":"non-"},{"w":"standard"},{"w":"deployment"},{"w":"patterns.","p":"sentence"},{"w":"Each"},{"w":"time,","p":"comma"},{"w":"the"},{"w":"CTO"},{"w":"has"},{"w":"intervened.","p":"sentence"},{"w":"This"},{"w":"tension"},{"w":"is"},{"w":"ongoing.","p":"paragraph"},{"w":"New"},{"w":"hires"},{"w":"take"},{"w":"time"},{"w":"to"},{"w":"adjust.","p":"sentence"},{"w":"People"},{"w":"from"},{"w":"traditional"},{"w":"corporates"},{"w":"expect"},{"w":"to"},{"w":"be"},{"w":"told"},{"w":"what"},{"w":"to"},{"w":"work"},{"w":"on.","p":"sentence"},{"w":"The"},{"w":"adjustment"},{"w":"can"},{"w":"take"},{"w":"three"},{"w":"to"},{"w":"six"},{"w":"months.","p":"paragraph"},{"w":"Financial"},{"w":"reporting"},{"w":"requires"},{"w":"translation.","p":"sentence"},{"w":"The"},{"w":"CFO's"},{"w":"team"},{"w":"redesigned"},{"w":"reporting"},{"w":"around"},{"w":"process-"},{"w":"level"},{"w":"cost"},{"w":"data.","p":"sentence"},{"w":"This"},{"w":"took"},{"w":"six"},{"w":"months.","p":"sentence"},{"w":"Board"},{"w":"reporting"},{"w":"required"},{"w":"explanation.","p":"paragraph"},{"w":"The"},{"w":"model"},{"w":"requires"},{"w":"engineers"},{"w":"the"},{"w":"industry"},{"w":"does"},{"w":"not"},{"w":"reliably"},{"w":"produce.","p":"sentence"},{"w":"The"},{"w":"autonomous"},{"w":"unit"},{"w":"depends"},{"w":"on"},{"w":"engineers"},{"w":"who"},{"w":"understand"},{"w":"business"},{"w":"processes"},{"w":"deeply"},{"w":"enough"},{"w":"to"},{"w":"co-"},{"w":"own"},{"w":"them.","p":"sentence"},{"w":"Roughly"},{"w":"a"},{"w":"third"},{"w":"developed"},{"w":"this"},{"w":"capability"},{"w":"within"},{"w":"eighteen"},{"w":"months.","p":"sentence"},{"w":"Another"},{"w":"third"},{"w":"remained"},{"w":"valuable"},{"w":"as"},{"w":"specialists"},{"w":"paired"},{"w":"with"},{"w":"colleagues"},{"w":"who"},{"w":"held"},{"w":"the"},{"w":"business"},{"w":"context.","p":"sentence"},{"w":"The"},{"w":"honest"},{"w":"admission:","p":"comma"},{"w":"the"},{"w":"transition"},{"w":"timeline"},{"w":"is"},{"w":"set"},{"w":"by"},{"w":"how"},{"w":"quickly"},{"w":"the"},{"w":"organisation"},{"w":"can"},{"w":"develop"},{"w":"these"},{"w":"people.","p":"paragraph"},{"w":"What"},{"w":"Has"},{"w":"Changed","p":"heading"},{"w":"The"},{"w":"organisation's"},{"w":"meeting"},{"w":"load"},{"w":"has"},{"w":"dropped"},{"w":"by"},{"w":"approximately"},{"w":"60%,","p":"comma"},{"w":"and"},{"w":"engineer"},{"w":"retention"},{"w":"has"},{"w":"improved"},{"w":"markedly.","p":"sentence"},{"w":"Annual"},{"w":"engineering"},{"w":"turnover"},{"w":"fell"},{"w":"from"},{"w":"22%"},{"w":"to"},{"w":"9%.","p":"sentence"},{"w":"Exit"},{"w":"interview"},{"w":"data"},{"w":"shows"},{"w":"that"},{"w":"the"},{"w":"most"},{"w":"common"},{"w":"reason"},{"w":"for"},{"w":"leaving"},{"w":"has"},{"w":"shifted"},{"w":"from"},{"w":"“frustration"},{"w":"with"},{"w":"process”"},{"w":"or"},{"w":"“lack"},{"w":"of"},{"w":"impact”"},{"w":"to"},{"w":"“opportunity"},{"w":"elsewhere,”"},{"w":"which"},{"w":"is"},{"w":"a"},{"w":"normal"},{"w":"reason,","p":"comma"},{"w":"not"},{"w":"a"},{"w":"structural"},{"w":"indictment.","p":"paragraph"},{"w":"Time-"},{"w":"to-"},{"w":"production"},{"w":"for"},{"w":"changes"},{"w":"has"},{"w":"decreased,","p":"comma"},{"w":"but"},{"w":"more"},{"w":"importantly,","p":"comma"},{"w":"the"},{"w":"variance"},{"w":"has"},{"w":"decreased.","p":"sentence"},{"w":"Changes"},{"w":"within"},{"w":"a"},{"w":"unit's"},{"w":"boundary"},{"w":"take"},{"w":"days.","p":"sentence"},{"w":"Changes"},{"w":"across"},{"w":"boundaries"},{"w":"are"},{"w":"predictably"},{"w":"slower"},{"w":"but"},{"w":"bounded"},{"w":"and"},{"w":"visible.","p":"paragraph"},{"w":"What"},{"w":"changed"},{"w":"is"},{"w":"the"},{"w":"nature"},{"w":"of"},{"w":"the"},{"w":"imperfection.","p":"sentence"},{"w":"The"},{"w":"problems"},{"w":"that"},{"w":"remain"},{"w":"are"},{"w":"specific,","p":"comma"},{"w":"owned,","p":"comma"},{"w":"and"},{"w":"tractable.","p":"paragraph"},{"w":"Coda","p":"heading"},{"w":"Lisa"},{"w":"attends"},{"w":"a"},{"w":"process"},{"w":"review"},{"w":"on"},{"w":"a"},{"w":"Tuesday"},{"w":"morning.","p":"sentence"},{"w":"She"},{"w":"has"},{"w":"been"},{"w":"at"},{"w":"the"},{"w":"company"},{"w":"for"},{"w":"thirteen"},{"w":"years"},{"w":"now.","p":"sentence"},{"w":"The"},{"w":"meeting"},{"w":"is"},{"w":"twenty"},{"w":"minutes"},{"w":"long.","p":"sentence"},{"w":"There"},{"w":"are"},{"w":"no"},{"w":"slides.","p":"paragraph"},{"w":"The"},{"w":"claims"},{"w":"management"},{"w":"unit,","p":"comma"},{"w":"her"},{"w":"unit,","p":"comma"},{"w":"reviews"},{"w":"the"},{"w":"weekly"},{"w":"synthesis.","p":"sentence"},{"w":"There"},{"w":"is"},{"w":"a"},{"w":"drift"},{"w":"flag"},{"w":"on"},{"w":"the"},{"w":"document"},{"w":"verification"},{"w":"step.","p":"sentence"},{"w":"She"},{"w":"already"},{"w":"knows"},{"w":"about"},{"w":"it.","p":"sentence"},{"w":"She"},{"w":"raised"},{"w":"it"},{"w":"last"},{"w":"week"},{"w":"when"},{"w":"she"},{"w":"noticed"},{"w":"the"},{"w":"manual"},{"w":"check"},{"w":"was"},{"w":"not"},{"w":"reflected"},{"w":"in"},{"w":"the"},{"w":"process"},{"w":"definition.","p":"paragraph"},{"w":"An"},{"w":"engineer"},{"w":"on"},{"w":"her"},{"w":"team"},{"w":"updates"},{"w":"the"},{"w":"definition.","p":"sentence"},{"w":"The"},{"w":"change"},{"w":"is"},{"w":"committed"},{"w":"before"},{"w":"the"},{"w":"meeting"},{"w":"ends.","p":"paragraph"},{"w":"The"},{"w":"unit"},{"w":"discusses"},{"w":"whether"},{"w":"the"},{"w":"compliance"},{"w":"check"},{"w":"can"},{"w":"be"},{"w":"partially"},{"w":"automated.","p":"sentence"},{"w":"Tomasz,","p":"comma"},{"w":"the"},{"w":"unit's"},{"w":"compliance"},{"w":"specialist,","p":"comma"},{"w":"has"},{"w":"been"},{"w":"reviewing"},{"w":"the"},{"w":"document"},{"w":"types"},{"w":"that"},{"w":"pass"},{"w":"through"},{"w":"the"},{"w":"verification"},{"w":"step.","p":"sentence"},{"w":"He"},{"w":"identifies"},{"w":"which"},{"w":"ones"},{"w":"can"},{"w":"be"},{"w":"safely"},{"w":"automated:","p":"comma"},{"w":"standard"},{"w":"proof-"},{"w":"of-"},{"w":"loss"},{"w":"forms"},{"w":"and"},{"w":"police"},{"w":"reports"},{"w":"in"},{"w":"standard"},{"w":"formats"},{"w":"carry"},{"w":"low"},{"w":"regulatory"},{"w":"risk"},{"w":"and"},{"w":"have"},{"w":"consistent"},{"w":"structures.","p":"sentence"},{"w":"Non-"},{"w":"standard"},{"w":"submissions,","p":"comma"},{"w":"foreign-"},{"w":"language"},{"w":"documents,","p":"comma"},{"w":"and"},{"w":"anything"},{"w":"involving"},{"w":"disputed"},{"w":"liability"},{"w":"require"},{"w":"human"},{"w":"judgement.","p":"sentence"},{"w":"He"},{"w":"is"},{"w":"specific"},{"w":"about"},{"w":"the"},{"w":"boundary"},{"w":"and"},{"w":"the"},{"w":"regulatory"},{"w":"basis"},{"w":"for"},{"w":"it.","p":"paragraph"},{"w":"Lisa"},{"w":"builds"},{"w":"on"},{"w":"his"},{"w":"assessment.","p":"sentence"},{"w":"She"},{"w":"has"},{"w":"been"},{"w":"looking"},{"w":"at"},{"w":"the"},{"w":"document"},{"w":"classification"},{"w":"model"},{"w":"that"},{"w":"the"},{"w":"data"},{"w":"platform"},{"w":"team"},{"w":"provides,","p":"comma"},{"w":"and"},{"w":"she"},{"w":"believes"},{"w":"it"},{"w":"can"},{"w":"handle"},{"w":"the"},{"w":"cases"},{"w":"Tomasz"},{"w":"has"},{"w":"cleared,","p":"comma"},{"w":"with"},{"w":"manual"},{"w":"review"},{"w":"reserved"},{"w":"for"},{"w":"everything"},{"w":"he"},{"w":"has"},{"w":"flagged.","p":"sentence"},{"w":"She"},{"w":"describes"},{"w":"the"},{"w":"technical"},{"w":"approach.","p":"sentence"},{"w":"Someone"},{"w":"asks"},{"w":"her"},{"w":"to"},{"w":"go"},{"w":"deeper"},{"w":"into"},{"w":"the"},{"w":"implementation"},{"w":"detail.","p":"sentence"},{"w":"Tomasz"},{"w":"confirms"},{"w":"the"},{"w":"compliance"},{"w":"constraints.","p":"sentence"},{"w":"The"},{"w":"team"},{"w":"agrees"},{"w":"to"},{"w":"prototype"},{"w":"it.","p":"sentence"},{"w":"Lisa"},{"w":"will"},{"w":"lead"},{"w":"the"},{"w":"implementation;","p":"comma"},{"w":"Tomasz"},{"w":"will"},{"w":"validate"},{"w":"the"},{"w":"automation"},{"w":"boundary"},{"w":"against"},{"w":"the"},{"w":"regulatory"},{"w":"requirements.","p":"paragraph"},{"w":"There"},{"w":"are"},{"w":"no"},{"w":"twelve"},{"w":"items"},{"w":"on"},{"w":"a"},{"w":"list"},{"w":"that"},{"w":"cannot"},{"w":"be"},{"w":"mapped"},{"w":"to"},{"w":"systems.","p":"sentence"},{"w":"There"},{"w":"is"},{"w":"one"},{"w":"process,","p":"comma"},{"w":"with"},{"w":"explicit"},{"w":"states"},{"w":"and"},{"w":"transitions,","p":"comma"},{"w":"owned"},{"w":"by"},{"w":"the"},{"w":"people"},{"w":"who"},{"w":"understand"},{"w":"it.","p":"sentence"},{"w":"When"},{"w":"Lisa"},{"w":"identifies"},{"w":"an"},{"w":"improvement,","p":"comma"},{"w":"she"},{"w":"does"},{"w":"not"},{"w":"need"},{"w":"to"},{"w":"convince"},{"w":"someone"},{"w":"in"},{"w":"another"},{"w":"department"},{"w":"to"},{"w":"prioritise"},{"w":"it.","p":"sentence"},{"w":"She"},{"w":"does"},{"w":"not"},{"w":"need"},{"w":"to"},{"w":"translate"},{"w":"her"},{"w":"insight"},{"w":"into"},{"w":"a"},{"w":"language"},{"w":"designed"},{"w":"for"},{"w":"people"},{"w":"who"},{"w":"cannot"},{"w":"see"},{"w":"the"},{"w":"system.","p":"sentence"},{"w":"She"},{"w":"describes"},{"w":"what"},{"w":"she"},{"w":"sees,","p":"comma"},{"w":"proposes"},{"w":"a"},{"w":"change,","p":"comma"},{"w":"and"},{"w":"her"},{"w":"team"},{"w":"decides.","p":"paragraph"},{"w":"By"},{"w":"operating"},{"w":"within"},{"w":"explicitly"},{"w":"defined"},{"w":"contracts,","p":"comma"},{"w":"the"},{"w":"team"},{"w":"functions"},{"w":"without"},{"w":"constantly"},{"w":"seeking"},{"w":"external"},{"w":"permissions.","p":"paragraph"},{"w":"The"},{"w":"structural"},{"w":"problems"},{"w":"never"},{"w":"entirely"},{"w":"disappear,","p":"comma"},{"w":"but"},{"w":"they"},{"w":"are"},{"w":"different"},{"w":"problems"},{"w":"now:","p":"comma"},{"w":"problems"},{"w":"that"},{"w":"can"},{"w":"be"},{"w":"seen,","p":"comma"},{"w":"named,","p":"comma"},{"w":"and"},{"w":"solved"},{"w":"by"},{"w":"the"},{"w":"people"},{"w":"closest"},{"w":"to"},{"w":"them.","p":"sentence"},{"w":"The"},{"w":"system"},{"w":"no"},{"w":"longer"},{"w":"resists"},{"w":"clarity.","p":"sentence"},{"w":"It"},{"w":"depends"},{"w":"on"},{"w":"it.","p":"paragraph"},{"w":"Three"},{"w":"people"},{"w":"she"},{"w":"has"},{"w":"worked"},{"w":"with"},{"w":"for"},{"w":"a"},{"w":"decade"},{"w":"are"},{"w":"gone.","p":"sentence"},{"w":"Two"},{"w":"left"},{"w":"voluntarily.","p":"sentence"},{"w":"One"},{"w":"was"},{"w":"asked"},{"w":"to"},{"w":"leave.","p":"paragraph"},{"w":"Lisa"},{"w":"finishes"},{"w":"her"},{"w":"coffee,","p":"comma"},{"w":"opens"},{"w":"her"},{"w":"editor,","p":"comma"},{"w":"and"},{"w":"tells"},{"w":"the"},{"w":"agent"},{"w":"what"},{"w":"needs"},{"w":"to"},{"w":"change.","p":"paragraph"},{"w":"It"},{"w":"is"},{"w":"a"},{"w":"Tuesday.","p":"paragraph"}]